Workbook
Name \1: #REF!
Name \1: #REF!
Name \2: #REF!
Name \A: [1]RS!#REF!
Name \A: [1]RS!#REF!
Name \A: #REF!
Name \b: #REF!
Name \b: #REF!
Name \b: #REF!
Name \b: #REF!
Name \B: #REF!
Name \b: #REF!
Name \C: #REF!
Name \C: #REF!
Name \C: #REF!
Name \C: #REF!
Name \c: #REF!
Name \C: #REF!
Name \D: #REF!
Name \D: #REF!
Name \e: #REF!
Name \F: #REF!
Name \G: #REF!
Name \H: #REF!
Name \i: #REF!
Name \i: #REF!
Name \i: #REF!
Name \i: #REF!
Name \J: #REF!
Name \K: #REF!
Name \l: #REF!
Name \l: #REF!
Name \l: #REF!
Name \l: #REF!
Name \m: #N/A
Name \M: #REF!
Name \M: #REF!
Name \M: #REF!
Name \n: #REF!
Name \n: #REF!
Name \n: #REF!
Name \n: #REF!
Name \O: #REF!
Name \P: #REF!
Name \Q: #REF!
Name \R: #REF!
Name \s: #REF!
Name \s: #REF!
Name \S: '[2]F&F'!#REF!
Name \s: #REF!
Name \s: #REF!
Name \S: '[2]F&F'!#REF!
Name \s: #REF!
Name \t: #REF!
Name \t: #REF!
Name \t: #REF!
Name \t: #REF!
Name \t: #REF!
Name \u: #REF!
Name \U: #REF!

Sheet Updated Trial 13
A2: SWIFT MOVERS (PVT.) LTD.
A4: Detailed Trial Balance
D6: Trial Balance KHI | F6: Trial Balance LHR | H6: Adjustment | J6: Adjusted Trial
A7: Account Name | D7: Debit | E7: Credit | F7: Debit | G7: Credit | H7: Debit | I7: Credit | J7: Debit | K7: Credit
A10: ASSETS
A11: CURRENT ASSETS
B12: CASH
A13: 1020101 | C13: CASH BOOK | D13: 1608.147 | F13: 11128 | J13: =(D13+F13+H13)-(E13+G13+I13) -> 12736.147
B15: BANK
A16: 1020203 | C16: BANK ALHABIB DOLLAR A/C | D16: 2009 | J16: =(D16+F16+H16)-(E16+G16+I16) -> 2009
A17: 1020204 | C17: BANK ALHABIB RUPEES A/C | D17: 4906.47 | J17: =(D17+F17+H17)-(E17+G17+I17) -> 4906.47
A18: 1020207 | C18: BANK ALHABIB RUPEES A/C (SSF) | D18: 470808 | I18: 100 | J18: =(D18+F18+H18)-(E18+G18+I18) -> 470708
A19: 1020201 | C19: FAYSAL BANK DOLLAR A/C | D19: 60643.25 | J19: =(D19+F19+H19)-(E19+G19+I19) -> 60643.25
A20: 1020202 | C20: FAYSAL BANK RUPEES A/C | D20: 624910.15 | J20: =(D20+F20+H20)-(E20+G20+I20) -> 624910.15
A21: Lhr | C21: BANK ALHABIB 095-01 | F21: 25374.55 | J21: =(D21+F21+H21)-(E21+G21+I21) -> 25374.55
B23: PETTY CASH
A24: 1020301 | C24: PETTY CASH BOOK | D24: 1882 | J24: =(D24+F24+H24)-(E24+G24+I24) -> 1882
B26: Advance Tax
A27: 1020420 | C27: ADVANCE INCOME TAX TELEPHONE | D27: 9554 | J27: =(D27+F27+H27)-(E27+G27+I27) -> 9554
A28: 1020422 | C28: ADVANCE INCOME TAXELECTRIC CHARGES | D28: 20306 | F28: 8000 | H28: ='Adj entry 13'!B26 -> 150 | I28: ='Adj entry 13'!C33 -> 1001 | J28: =(D28+F28+H28)-(E28+G28+I28) -> 27455
A29: 1020426 | C29: ADVANCE INCOMETAX - CASH WITHDRAWL | D29: 6956.8 | J29: =(D29+F29+H29)-(E29+G29+I29) -> 6956.8
A30: 1020425 | C30: ADVANCE INCOMTAX - MOBILE | D30: 6960 | H30: ='Adj entry 13'!B19 -> 11058 | J30: =(D30+F30+H30)-(E30+G30+I30) -> 18018
A31: Lhr | C31: DEFERRED TAX ASSETS | F31: 900708 | H31: -176364 | J31: =(D31+F31+H31)-(E31+G31+I31) -> 724344
A32: Lhr | C32: INCOME TAX REFUNDABLE (Asset) | F32: =132136+246068 -> 378204 | J32: =(D32+F32+H32)-(E32+G32+I32) -> 378204
A33: Lhr | C33: PROVISION FOR CURRENT TAX | I33: ='Adj entry 13'!C5 -> #REF! | K33: =(E33+G33+I33)-(D33+F33+H33) -> #REF!
A34: Lhr | C34: DEFERRED TAX | F34: 505428 | J34: =(D34+F34+H34)-(E34+G34+I34) -> 505428
C35: DEFFERD TAX INCOME 2013 | I35: =-'Adj entry 13'!C11 -> #REF! | K35: =(E35+G35+I35)-(D35+F35+H35) -> #REF!
B37: ADVANCE DEPOSITS & PREPAYMENTS
A38: 1020417 | C38: MR ADNAN | D38: 37500 | J38: =(D38+F38+H38)-(E38+G38+I38) -> 37500
A39: 1020432 | C39: MR. ALI SHER | D39: 10000 | J39: =(D39+F39+H39)-(E39+G39+I39) -> 10000
A40: 1020430 | C40: MR. MAHFOOZ | D40: 6000 | J40: =(D40+F40+H40)-(E40+G40+I40) -> 6000
A41: 1020434 | C41: MR. RAMISH MUKADAM | D41: 5000 | J41: =(D41+F41+H41)-(E41+G41+I41) -> 5000
A42: 1020412 | C42: MR.ZOHAIB | D42: 11500 | J42: =(D42+F42+H42)-(E42+G42+I42) -> 11500
C44: Insurance Prepaid | H44: ='Adj entry 13'!B22 -> 22144 | J44: =(D44+F44+H44)-(E44+G44+I44) -> 22144
B46: Secutity Deposits
A47: 1020408 | C47: SECURITY DEPOSIT MOBILE | D47: 18500 | J47: =(D47+F47+H47)-(E47+G47+I47) -> 18500
A48: 1020409 | C48: SECURITY DEPOSIT OFFICE | D48: 42000 | J48: =(D48+F48+H48)-(E48+G48+I48) -> 42000
A49: 1020206 | C49: SECURITY DEPOSIT (NESTLE) | F49: 1000 | J49: =(D49+F49+H49)-(E49+G49+I49) -> 1000
A50: 1020202 | C50: SECURITY DEPOSIT-OFFICE | F50: 150000 | J50: =(D50+F50+H50)-(E50+G50+I50) -> 150000
A51: 1020203 | C51: SECURITY DEPOSIT-PUMP | F51: 5000 | J51: =(D51+F51+H51)-(E51+G51+I51) -> 5000
A54: FIXED ASSETS
B55: TANGIBLE ASSETS
A56: 1010102 | C56: COMPUTER & ACCESSORIES | D56: 153815 | F56: 266015 | J56: =(D56+F56+H56)-(E56+G56+I56) -> 419830
A57: 1010101 | C57: FURNITURE & FIXTURE | D57: 107951 | F57: 214000 | J57: =(D57+F57+H57)-(E57+G57+I57) -> 321951
A58: 1010106 | C58: GENRATOR | D58: 155250 | J58: =(D58+F58+H58)-(E58+G58+I58) -> 155250
A59: 1010104 | C59: MOTOR CYCLE | D59: 38000 | F59: 35000 | J59: =(D59+F59+H59)-(E59+G59+I59) -> 73000
A60: 1010105 | C60: MOTOR VEHICLE-LEASED (CULTUS) | D60: 600000 | J60: =(D60+F60+H60)-(E60+G60+I60) -> 600000
A61: 1010103 | C61: OFFICE EQUIPMENTS | D61: 457586 | F61: 201800 | J61: =(D61+F61+H61)-(E61+G61+I61) -> 659386
A62: 1010108 | C62: VEHICLE LEASED (HONDA CITY) | D62: 1270675 | J62: =(D62+F62+H62)-(E62+G62+I62) -> 1270675
A65: OTHER ASSETS
B66: TRADE DEBITORS
A67: 10301267 | C67: AL GRETA SOLUTION | D67: 221463 | J67: =(D67+F67+H67)-(E67+G67+I67) -> 221463
A68: 10301294 | C68: CONNECTORS INC | D68: 8575 | J68: =(D68+F68+H68)-(E68+G68+I68) -> 8575
A69: 1030186 | C69: DAMCO GERMANY | D69: 24166.54 | J69: =(D69+F69+H69)-(E69+G69+I69) -> 24166.54
A70: 10301228 | C70: DELMAR INTERNATIONAL | D70: 1068976.3 | J70: =(D70+F70+H70)-(E70+G70+I70) -> 1068976.3
A71: 10301176 | C71: DK INDUSTRIES PVT | D71: 3500 | J71: =(D71+F71+H71)-(E71+G71+I71) -> 3500
A72: 10301308 | C72: ENERGY INTERNATIONAL LOGISTICS SRL | D72: 26730 | J72: =(D72+F72+H72)-(E72+G72+I72) -> 26730
A73: 10301265 | C73: EURO TEXTILES | D73: 314584 | J73: =(D73+F73+H73)-(E73+G73+I73) -> 314584
A74: 10301324 | C74: GAUNTLET SPORTS | D74: 13265 | J74: =(D74+F74+H74)-(E74+G74+I74) -> 13265
A75: 1030163 | C75: GERBRUEDER WEISS GMBH | D75: 4900 | J75: =(D75+F75+H75)-(E75+G75+I75) -> 4900
A76: 10301360 | C76: HENNYS PRIVATE LIMITED | D76: 442332 | J76: =(D76+F76+H76)-(E76+G76+I76) -> 442332
A77: 10301174 | C77: INTERCLEAN COMMERCIAL | D77: 81715 | J77: =(D77+F77+H77)-(E77+G77+I77) -> 81715
A78: 10301105 | C78: INTERNATIONAL INDUSTRY | D78: 19894 | J78: =(D78+F78+H78)-(E78+G78+I78) -> 19894
A79: 10301151 | C79: IRSHAD TANNING WORKS | D79: 494496 | J79: =(D79+F79+H79)-(E79+G79+I79) -> 494496
A80: 10301349 | B80: Advance from customers | C80: JHJ INTERNATIONAL | E80: 235545.33 | K80: =(E80+G80+I80)-(D80+F80+H80) -> 235545.33
A81: 10301213 | C81: JNS IMPEX | D81: 47400 | J81: =(D81+F81+H81)-(E81+G81+I81) -> 47400
A82: 10301278 | C82: KARLOS IND | D82: 1900 | J82: =(D82+F82+H82)-(E82+G82+I82) -> 1900
A83: 10301138 | C83: KNITWEAR ENTERPRISES | D83: 354236 | J83: =(D83+F83+H83)-(E83+G83+I83) -> 354236
A84: 10301318 | C84: L V SHIPPING LTD | D84: 250323.73 | J84: =(D84+F84+H84)-(E84+G84+I84) -> 250323.73
A85: 1030143 | C85: M TAYYAB M TAHIR DYES | D85: 19000 | J85: =(D85+F85+H85)-(E85+G85+I85) -> 19000
A86: 10301256 | C86: MAC LOGISTICS | D86: 53599 | J86: =(D86+F86+H86)-(E86+G86+I86) -> 53599
A87: 10301321 | C87: MANAKIN TEXTILES | D87: 3200 | J87: =(D87+F87+H87)-(E87+G87+I87) -> 3200
A88: 1030196 | C88: MASF SHIPPING SERVICES | D88: 254991 | J88: =(D88+F88+H88)-(E88+G88+I88) -> 254991
A89: 10301207 | C89: METRO FREIGHT INTERNATIONAL | D89: 132701.07 | J89: =(D89+F89+H89)-(E89+G89+I89) -> 132701.07
A90: 1030110 | C90: PELIKAN KNITWEAR | D90: 294000 | J90: =(D90+F90+H90)-(E90+G90+I90) -> 294000
A91: 10301361 | C91: PENGELL YS LTD | D91: 2940 | J91: =(D91+F91+H91)-(E91+G91+I91) -> 2940
A92: 10301269 | C92: POSTEN LOGISTICS AB | D92: 1008.75 | J92: =(D92+F92+H92)-(E92+G92+I92) -> 1008.75
... A104: 10301303 | C104: UNIQUE LOGISTICS INTERNATIONAL INC | D104: 4485 | J104: =(D104+F104+H104)-(E104+G104+I104) -> 4485
B106: BRANCHES
A107: 1030205 | C107: FAISALABAD OFFICE | D107: 9562.2 | J107: =(D107+F107+H107)-(E107+G107+I107) -> 9562.2
A108: 1030201 | C108: GUL AVIATION | E108: 1351430.3 | K108: =(E108+G108+I108)-(D108+F108+H108) -> 1351430.3
A109: 1030203 | C109: LAHORE OFFICE (Net off) | D109: 9429494 | I109: ='Adj entry 13'!C14 -> 9429494 | J109: =(D109+F109+H109)-(E109+G109+I109) -> 0
A110: 1030204 | C110: SIALKOT OFFICE | D110: 517678 | J110: =(D110+F110+H110)-(E110+G110+I110) -> 517678
A111: 1030202 | C111: SWIFT INTERNATIONAL | D111: 254870 | J111: =(D111+F111+H111)-(E111+G111+I111) -> 254870
A115: LIABLITIES
A116: CURRENT LIABILITIES
B117: ACCRUED EXPENSES
A118: 3010111 | C118: EXPENSES PAYABLE | E118: 622318 | K118: =(E118+G118+I118)-(D118+F118+H118) -> 622318
A119: 3010109 | C119: STAFF SAVINGS PAYABLE | E119: 470808 | H119: 100 | K119: =(E119+G119+I119)-(D119+F119+H119) -> 470708
A120: Lhr | C120: ACCURED EXPENSES | G120: 86100 | H120: ='Adj entry 13'!B23 -> 69398 | I120: ='Adj entry 13'!C30+'Adj entry 13'!C36+'Adj entry 13'!C39 -> 25268 | K120: =(E120+G120+I120)-(D120+F120+H120) -> 41970
A123: OTHER LIABLITIES
B124: TRADE CREDITORS
A125: 3030121 | C125: ASKARI BANK LTD. HONDA CITY | E125: 1607 | K125: =(E125+G125+I125)-(D125+F125+H125) -> 1607
A126: 3030102 | C126: CARGO CORPORATION | E126: 23230 | K126: =(E126+G126+I126)-(D126+F126+H126) -> 23230
A127: 3030123 | C127: GULSONS EXPRESS (PVT) LTD | E127: 38372 | K127: =(E127+G127+I127)-(D127+F127+H127) -> 38372
A128: 3030110 | C128: PIONEER EXPRESS (PVT) LTD. | E128: 935410 | K128: =(E128+G128+I128)-(D128+F128+H128) -> 935410
A129: 3030130 | C129: PORTLINK | E129: 100005 | K129: =(E129+G129+I129)-(D129+F129+H129) -> 100005
A130: 3030131 | C130: PRANTIK EXPRESS LTD | E130: 439685 | K130: =(E130+G130+I130)-(D130+F130+H130) -> 439685
A131: 3030126 | C131: R.K ENGINEERING | E131: 79694 | K131: =(E131+G131+I131)-(D131+F131+H131) -> 79694
A132: 3030132 | C132: SAMER & CO SHIPPING SRL | E132: 24960 | K132: =(E132+G132+I132)-(D132+F132+H132) -> 24960
...

Sheet Adj entry 13
A1: Swift Movers (Pvt) Limited
A2: Adjusting entries for the year ended on 30 June, 2013
A3: Particulars | B3: Debit | C3: Credit | D3: Refferd Trial | E3: Client trial
A4: Provision for Current tax | B4: ='C.tax computation'!K34 -> #REF! | E4: Lahore
A5: Tax Refund Due form Govt | C5: =B4 -> #REF! | E5: Lahore
B6: =SUM(B4:B5) -> #REF! | C6: =SUM(C4:C5) -> #REF! | D6: POSTED
A7: Acc.Depreciation Computer Assecories | B7: 417 | E7: Lahore
A8: Depreciation (Administrative Expense) | C8: =B7 -> 417 | E8: Lahore
B9: =SUM(B7:B8) -> 417 | C9: =SUM(C7:C8) -> 417 | D9: POSTED
A10: Defferd Tax expense | B10: ='Def tax'!H64 -> #REF! | E10: Lahore
A11: Defferd tax asset | C11: =B10 -> #REF! | E11: Lahore
B12: =SUM(B10:B11) -> #REF! | C12: =SUM(C10:C11) -> #REF! | D12: POSTED
A13: Swift Movers ltd Karachi | B13: 9429494 | E13: Karachi
A14: Swift Movers Lahore | C14: =B13 -> 9429494 | E14: Karachi
B15: =SUM(B13:B14) -> 9429494 | C15: =SUM(C13:C14) -> 9429494 | D15: POSTED
A16: Eobi | B16: 0 | E16: Karachi
A17: Staff Salary | C17: =B16 -> 0 | E17: Karachi
B18: =SUM(B16:B17) -> 0 | C18: =SUM(C16:C17) -> 0 | D18: POSTED
A19: Advance Tax Mobile | B19: 11058 | E19: Karachi
A20: Mobile Charges | C20: =B19 -> 11058 | E20: Karachi
B21: =SUM(B19:B20) -> 11058 | C21: =SUM(C19:C20) -> 11058 | D21: POSTED
A22: Prepaid Insurance | B22: 22144 | E22: Karachi | F22: 22144
A23: Expenses Payable | B23: 69398 | E23: Lahore | F23: 69398
A24: Insurance Expense | C24: 91542 | E24: Karachi | G24: 91542
B25: =SUM(B22:B24) -> 91542 | C25: =SUM(C22:C24) -> 91542 | D25: POSTED
A26: Advance Tax On Electricity | B26: 150 | E26: Lahore
A27: Electricity Expense | C27: 150 | E27: Lahore
B28: =SUM(B26:B27) -> 150 | C28: =SUM(C26:C27) -> 150 | D28: POSTED
A29: Electricity Expense | B29: 5992 | E29: Lahore
A30: Expenses Payable | C30: 5992 | E30: Lahore
B31: =SUM(B29:B30) -> 5992 | C31: =SUM(C29:C30) -> 5992 | D31: POSTED
A32: Electricity expense | B32: 1001 | E32: Karachi
A33: Advance Tax Electricity | C33: 1001 | E33: Karachi
B34: =SUM(B32:B33) -> 1001 | C34: =SUM(C32:C33) -> 1001 | D34: POSTED
A35: Electricity expense | B35: 10576 | E35: Karachi
A36: Expense Payable | C36: 10576 | E36: Karachi
B37: =SUM(B35:B36) -> 10576 | C37: =SUM(C35:C36) -> 10576 | D37: POSTED
A38: Telephone Expense | B38: 8700 | E38: Karachi
A39: Expense Payable | C39: 8700 | E39: Karachi
B40: =SUM(B38:B39) -> 8700 | C40: =SUM(C38:C39) -> 8700 | D40: POSTED

Sheet Trial Combine 19
A1: =SOFP!A1 -> AIMAL KHAN TRADERS
A2: TRIAL BALANCE AS AT 30 JUNE, 2019
C6: KARACHI OFFICE | E6: LAHORE OFFICE | G6: ADJUSTING ENTRIES | I6: ADJUSTED TRIAL
C7: Debit | D7: Credit | E7: Debit | F7: Credit | G7: Debit | H7: Credit | I7: Debit | J7: Credit
A8: CASH
A9: 1020101 | B9: CASH BOOK | C9: 8925 | D9: 0 | E9: 0 | I9: =C9+G9 -> 8925 | J9: =D9+H9 -> 0
A10: 1020301 | B10: CASH BOOK | I10: =C10+G10 -> 0 | J10: =D10+H10 -> 0
A11: BANK | I11: =C11+G11 -> 0 | J11: =D11+H11 -> 0
A12: 1020203 | B12: BANK ALHABIB DOLLAR A/C | I12: =C12+G12 -> 0 | J12: =D12+H12 -> 0
A13: 1020204 | B13: BANK ALHABIB RUPEES A/C | C13: 0 | G13: 0 | I13: =C13+G13 -> 0 | J13: =D13+H13 -> 0
B14: cash at bank | C14: 515289.57 | I14: =C14+G14 -> 515289.57 | J14: =D14+H14 -> 0
A15: 1020207 | B15: BANK ALHABIB RUPEES A/C (SSF) | C15: 0 | H15: ='Adj entry 19'!D30 -> 0 | I15: =C15+G15 -> 0 | J15: =D15+H15 -> 0
A16: 1020201 | B16: FAYSAL BANK DOLLAR A/C | C16: 0 | G16: ='Adj entry 19'!C22 -> 0 | I16: =C16+G16 -> 0 | J16: =D16+H16 -> 0
A17: 1020202 | B17: FAYSAL BANK RUPEES A/C | C17: 0 | I17: =C17+G17 -> 0 | J17: =D17+H17 -> 0
A18: 1020101 | B18: BANK AL HABIB 095-01 | C18: 0 | E18: 0 | G18: 0 | H18: ='Adj entry 19'!D17 -> 0 | I18: =C18+G18 -> 0 | J18: =D18+H18 -> 0
I19: =C19+G19 -> 0 | J19: =D19+H19 -> 0
A20: ADVANCE TAX | C20: 0 | I20: =C20+G20 -> 0 | J20: =D20+H20 -> 0
B21: wht on bank profit and cash withdrawl | C21: 15041.15 | I21: =C21+G21 -> 15041.15 | J21: =D21+H21 -> 0
A22: 1020201 | B22: ADVANCE INCOME TAX | C22: 0 | E22: 0 | H22: 0 | I22: =C22+G22 -> 0 | J22: =D22+H22 -> 0 | L22: =41180+23406+100432+39432 -> 204450 | M22: =H22-L22 -> -204450
A23: 1020211 | B23: ADVANCE INCOME TAX ELECTRIC | C23: 0 | E23: 0 | H23: 0 | I23: =C23+G23 -> 0 | J23: =D23+H23 -> 0
A24: 1020213 | B24: ADVANCE INCOME TAX MOBILE | C24: 0 | E24: 0 | H24: 0 | I24: =C24+G24 -> 0 | J24: =D24+H24 -> 0 | K24: =356475-344646 -> 11829
A25: 1020212 | B25: ADVANCE INCOME TAX ON CASH WITHDRAWAL | C25: 0 | E25: 0 | H25: 0 | I25: =C25+G25 -> 0 | J25: =D25+H25 -> 0
A26: 1020209 | B26: ADVANCE INCOME TAX ON TELE PH | C26: 0 | E26: 0 | H26: 0 | I26: =C26+G26 -> 0 | J26: =D26+H26 -> 0
A27: 1020420 | B27: ADVANCE INCOME TAX TELEPHONE | C27: 0 | E27: 0 | I27: =C27+G27 -> 0 | J27: =D27+H27 -> 0
A28: 1020429 | B28: ADVANCE INCOME TAX VEHICLE | C28: 0 | E28: 0 | I28: =C28+G28 -> 0 | J28: =D28+H28 -> 0
A29: 1020422 | B29: ADVANCE INCOME TAXELECTRIC CHARGES | C29: 0 | I29: =C29+G29 -> 0 | J29: =D29+H29 -> 0
A30: 1020426 | B30: ADVANCE INCOMETAX - CASH WITHDRAWL | C30: 0 | I30: =C30+G30 -> 0 | J30: =D30+H30 -> 0 | L30: =655+32138 -> 32793
A31: 1020425 | B31: ADVANCE INCOMTAX - MOBILE | C31: 0 | I31: =C31+G31 -> 0 | J31: =D31+H31 -> 0 | L31: =2322+516+3874 -> 6712
B32: REFUNDABLE INCOME TAX | C32: 0 | E32: 0 | G32: 0 | H32: 0 | I32: =C32+G32 -> 0 | J32: =D32+H32 -> 0
A33: 1020214 | B33: DEFERRED TAX ASSETS | C33: 0 | E33: 0 | G33: 0 | I33: =C33+G33 -> 0 | J33: =D33+H33 -> 0
A34: 1020207 | B34: INCOME TAX U/S 137 | C34: 0 | H34: =+'Adj entry 19'!D45 -> 0 | I34: =C34+G34 -> 0 | J34: =D34+H34 -> 0
B35: CURRENT YEAR INCOME TAX PROVISION REFUNDABLE / (PAYABLE) | F35: 0 | G35: 0 | H35: ='Adj entry 19'!D7 -> #REF! | I35: =C35+G35 -> 0 | J35: =D35+H35 -> #REF! | L35: =J213+H35 -> #REF!
I36: =C36+G36 -> 0 | J36: =D36+H36 -> 0
A37: ADVANCE DEPOSITS & PREPAYMENTS | I37: =C37+G37 -> 0 | J37: =D37+H37 -> 0
A38: 1020417 | B38: MR ADNAN | C38: 0 | I38: =C38+G38 -> 0 | J38: =D38+H38 -> 0 | N38: =I35-SOFP!#REF! -> #REF!
A39: 1020430 | B39: MR. MAHFOOZ | C39: 0 | I39: =C39+G39 -> 0 | J39: =D39+H39 -> 0
A40: 1020412 | B40: MR.ZOHAIB | I40: =C40+G40 -> 0 | J40: =D40+H40 -> 0
A41: 1020439 | B41: MUJTABA PARACHA | I41: =C41+G41 -> 0 | J41: =D41+H41 -> 0
A42: 1020431 | B42: RAHEEL UMAIR | I42: =C42+G42 -> 0 | J42: =D42+H42 -> 0
B43: security deposits | C43: 1200000 | I43: =C43+G43 -> 1200000 | J43: =D43+H43 -> 0
A44: 1020408 | B44: SECURITY DEPOSIT MOBILE | C44: 0 | I44: =C44+G44 -> 0 | J44: =D44+H44 -> 0
A45: 1020409 | B45: SECURITY DEPOSIT OFFICE - lhr | C45: 0 | E45: 0 | H45: ='Adj entry 19'!D27 -> 0 | I45: =C45+G45 -> 0 | J45: =D45+H45 -> 0
A46: 1020203 | B46: SECURITY DEPOSIT-PUMP | C46: 0 | E46: 0 | I46: =C46+G46 -> 0 | J46: =D46+H46 -> 0
A47: 1020206 | B47: SECURITY DEPOSIT (NESTLE) | E47: 0 | I47: =C47+G47 -> 0 | J47: =D47+H47 -> 0
A48: 1020428 | B48: Prepaid Insurance | I48: =C48+G48 -> 0 | J48: =D48+H48 -> 0
A49: 1020202 | B49: SECURITY DEPOSIT-OFFICE | I49: =C49+G49 -> 0 | J49: =D49+H49 -> 0
I50: =C50+G50 -> 0 | J50: =D50+H50 -> 0
A51: INVENTORY | I51: =C51+G51 -> 0 | J51: =D51+H51 -> 0
A52: inventory on hand | C52: 1586378.9 | I52: =C52+G52 -> 1586378.9 | J52: =D52+H52 -> 0
I53: =C53+G53 -> 0 | J53: =D53+H53 -> 0
A54: FIXED ASSETS | C54: 15147681 | I54: =C54+G54 -> 15147681 | J54: =D54+H54 -> 0
A55: TANGIBLE ASSETS | I55: =C55+G55 -> 0 | J55: =D55+H55 -> 0
B56: intangible assets | C56: 136126 | I56: =C56+G56 -> 136126 | J56: =D56+H56 -> 0
A57: 1010102 | B57: COMPUTER & ACCESSORIES | C57: 0 | E57: 0 | I57: =C57+G57 -> 0 | J57: =D57+H57 -> 0 | K57: =SUM(I57:I64) -> 0 | L57: =SUM(J274:J281) -> 0 | M57: =K57-L57 -> 0
A58: 1010101 | B58: FURNITURE & FIXTURE | C58: 0 | E58: 0 | I58: =C58+G58 -> 0 | J58: =D58+H58 -> 0
A59: 1010106 | B59: GENRATOR | C59: 0 | E59: 0 | I59: =C59+G59 -> 0 | J59: =D59+H59 -> 0
A60: 1010109 | B60: HONDA CITY - 2015 | C60: 0 | I60: =C60+G60 -> 0 | J60: =D60+H60 -> 0
A61: 1010104 | B61: MOTOR CYCLE | C61: 0 | E61: 0 | I61: =C61+G61 -> 0 | J61: =D61+H61 -> 0 | L61: =I60+I62+I64 -> 0
A62: 1010105 | B62: MOTOR VEHICLE-LEASED (CULTUS) | C62: 0 | I62: =C62+G62 -> 0 | J62: =D62+H62 -> 0
A63: 1010103 | B63: OFFICE EQUIPMENTS | C63: 0 | E63: 0 | I63: =C63+G63 -> 0 | J63: =D63+H63 -> 0
A64: 1010108 | B64: VEHICLE LEASED (HONDA CITY) | C64: 0 | I64: =C64+G64 -> 0 | J64: =D64+H64 -> 0
A65: 1010201 | B65: FURNITURE & FIXTURE | I65: =C65+G65 -> 0 | J65: =D65+H65 -> 0
A66: 1010301 | B66: MOTOR CYCLE | I66: =C66+G66 -> 0 | J66: =D66+H66 -> 0
A67: 1010501 | B67: OFFICE EQUIPMENTS | I67: =C67+G67 -> 0 | J67: =D67+H67 -> 0
I68: =C68+G68 -> 0 | J68: =D68+H68 -> 0
I69: =C69+G69 -> 0 | J69: =D69+H69 -> 0
I70: =C70+G70 -> 0 | J70: =D70+H70 -> 0
I71: =C71+G71 -> 0 | J71: =D71+H71 -> 0
A72: OTHER ASSETS | I72: =C72+G72 -> 0 | J72: =D72+H72 -> 0
A73: TRADE DEBITORS | I73: =C73+G73 -> 0 | J73: =D73+H73 -> 0
B74: AKZO NOBEL PAKISTAN LIMITED | C74: 0 | I74: =C74+G74 -> 0 | J74: =D74+H74 -> 0
A75: 10301663 | B75: AGRO HUB INTERNATIONAL (PVT) LTD | I75: =C75+G75 -> 0 | J75: =D75+H75 -> 0
B76: AHMED MANUFACTURING CORPORATION PVT LTD | I76: =C76+G76 -> 0 | J76: =D76+H76 -> 0
A77: 10301267 | B77: AL GRETA SOLUTION | C77: 0 | I77: =C77+G77 -> 0 | J77: =D77+H77 -> 0
B78: AL-KARAM TEXTILE MILLS (PVT.)LTD. | C78: 0 | I78: =C78+G78 -> 0 | J78: =D78+H78 -> 0
B79: AL RAHEEM TEXTILE INDUSTRIES | C79: 0 | I79: =C79+G79 -> 0 | J79: =D79+H79 -> 0
B80: Ariston tradelinks | C80: 0 | I80: =C80+G80 -> 0 | J80: =D80+H80 -> 0
B81: AL RAYAHEEN TRADING | C81: 0 | I81: =C81+G81 -> 0 | J81: =D81+H81 -> 0
B82: AL NABOODAH CARGO CENTRE LLC | C82: 0 | D82: 0 | I82: =C82+G82 -> 0 | J82: =D82+H82 -> 0
A83: 10301686 | B83: AL-JABBER EXPORT | C83: 0 | I83: =C83+G83 -> 0 | J83: =D83+H83 -> 0
A84: 10301582 | B84: ALSONS INDUSTRIES (PVT) LTD | C84: 0 | I84: =C84+G84 -> 0 | J84: =D84+H84 -> 0
A85: 10301651 | B85: AMTECH | I85: =C85+G85 -> 0 | J85: =D85+H85 -> 0
A86: 10301703 | B86: AP LOGISTICS SP ZO.O | I86: =C86+G86 -> 0 | J86: =D86+H86 -> 0
A87: 10301439 | B87: AVION SHIPPING CO LTD | I87: =C87+G87 -> 0 | J87: =D87+H87 -> 0
A88: 10301377 | B88: BOTAN CORPORATION | I88: =C88+G88 -> 0 | J88: =D88+H88 -> 0
B89: BASF PAKISTAN PVT LTD | C89: 0 | I89: =C89+G89 -> 0 | J89: =D89+H89 -> 0
B90: BAZI KNITWEAR | C90: 0 | I90: =C90+G90 -> 0 | J90: =D90+H90 -> 0
B91: BEAU ELITE PRODUCTS | C91: 0 | I91: =C91+G91 -> 0 | J91: =D91+H91 -> 0
B92: BIG BIRD FOOD PVT LTD | C92: 0 | I92: =C92+G92 -> 0 | J92: =D92+H92 -> 0
A93: 10301195 | B93: CAB FORWARDING B.V | C93: 0 | I93: =C93+G93 -> 0 | J93: =D93+H93 -> 0
B94: CHISTI ENTERPRISES | I94: =C94+G94 -> 0 | J94: =D94+H94 -> 0
A95: 10301692 | B95: CHANNA ENERPRISES | I95: =C95+G95 -> 0 | J95: =D95+H95 -> 0
A96: 10301644 | B96: CHIPPA TEXTILES | I96: =C96+G96 -> 0 | J96: =D96+H96 -> 0
A97: 10301384 | B97: CHORUS LOGISTICS | C97: 0 | I97: =C97+G97 -> 0 | J97: =D97+H97 -> 0
B98: CHOUDHRI INTERNATIONAL | C98: 0 | I98: =C98+G98 -> 0 | J98: =D98+H98 -> 0
B99: CIROS ENTERPRISES | C99: 0 | I99: =C99+G99 -> 0 | J99: =D99+H99 -> 0
B100: COMMANDING OFFICER NAVAL | C100: 0 | I100: =C100+G100 -> 0 | J100: =D100+H100 -> 0
A101: 1030186 | B101: DAMCO GERMANY | C101: 0 | I101: =C101+G101 -> 0 | J101: =D101+H101 -> 0
B102: DAWOOD ENGINEERING PVT LTD | C102: 0 | I102: =C102+G102 -> 0 | J102: =D102+H102 -> 0
B103: DELTA INTERNATIONAL PVT LTD | C103: 0 | I103: =C103+G103 -> 0 | J103: =D103+H103 -> 0
...

Sheet Adj entry 19
A1: SWIFT MOVERS PVT LIMITED
A2: AUDIT FOR THE YEAR ENDED 30 JUNE, 2019
A3: ADJUSTING ENTRIES
A5: Sr.No | B5: Particulars | C5: Debit | D5: Credit | E5: City | F5: Status
A6: 1 | B6: Income tax Expense | C6: ='C.tax computation'!K34 -> #REF! | F6: Posted
B7: Income tax provision | D7: =C6 -> #REF!
A9: =A6+1 -> 2 | B9: Deffered tax expense | C9: ='Def tax'!H64 -> #REF! | F9: Posted
B10: deferred tax liability | D10: =SUM(C9:C9) -> #REF!
A12: =A9+1 -> 3 | B12: Audit fee | C12: 50000 | F12: Posted
B13: Audit fee payable | D13: =SUM(C12:C12) -> 50000
B14: Reason :
C15: 0 | F15: Posted
A16: 4 | B16: Advertisement Expense | C16: 0
B17: Bank | D17: =C16 -> 0
A19: 5 | B19: AUDIT FEES | C19: 0 | F19: Posted
B20: EXPENSES PAYABLE | D20: =C19 -> 0
H21: =37695-#REF! -> #REF!
A22: 6 | B22: cash in foreign currency | C22: 0 | F22: Posted
B23: exchange gain | D23: =C22 -> 0
A25: 7 | C25: 0 | E25: 0 | F25: Posted
B26: Rent expense | C26: 0 | D26: =C25 -> 0 | H26: =356475-#REF! -> #REF!
B27: ='Trial Combine 19'!B45 -> SECURITY DEPOSIT OFFICE - lhr | D27: 0
A28: 8 | B28: Payable to staff provident fund account | C28: 0 | F28: Posted
B29: Bank charges | D29: 0
B30: Bank Al habib limited -57-01-8 | D30: 0
A31: 9 | B31: Provision for taxation | C31: 0 | F31: Posted
B32: Refundable income tax | C32: 0
B33: ADVANCE INCOME TAX | D33: 0
B34: ADVANCE INCOME TAX ELECTRIC | D34: 0
B35: ADVANCE INCOME TAX-VEHICLE | D35: 0
B36: ADVANCE INCOME TAX ON CASH WITHDRAWAL | D36: 0
B37: ADVANCE INCOME TAX ON TELE PH | D37: 0
B38: ADVANCE INCOME TAX ON MOBILE | D38: 0
G39: 97353
C40: =SUM(C6:C39) -> #REF! | D40: =SUM(D6:D39) -> #REF!
D42: =C40-D40 -> #REF!
B43: Other expenses | C43: 0
B44: Entertainment | C44: 0
B45: Prior year tax | D45: =+C43+C44 -> 0

Sheet grouping
A1: SWIFT MOVERS PRIVATE LIMITED
A2: FOR THE PERIOD ENDED JUNE 30, 2019
A4: Property and equipment
A5: A/C Code | B5: Accounting Description | C5: R.F | D5: 2019 | E5: 2015 | F5: 2018
B7: COST
B8: FURNITURE AND FIXTURES | D8: ='FIXED ASSETS'!L11 -> 700000 | F8: 321951
B9: OFFICE EQUIPMENT | D9: ='FIXED ASSETS'!L12 -> 112428 | F9: 720786
B10: COMPUTERS | D10: ='FIXED ASSETS'!L15 -> 732000 | F10: 472830
B11: GENERATOR | D11: ='FIXED ASSETS'!L16 -> 1068000 | F11: 155250
B12: MOTOR VEHICLE | D12: ='FIXED ASSETS'!L17 -> 8780816 | F12: 3392675
B13: MOTOR CYCLE | D13: ='FIXED ASSETS'!#REF! -> #REF! | F13: 73000
D14: =SUM(D8:D13) -> #REF! | E14: =SUM(E8:E12) -> 0 | F14: 5136492
B16: ACC. DEPRECIATION
B17: FURNITURE AND FIXTURES | D17: ='FIXED ASSETS'!X11 -> 35000 | F17: ='FIXED ASSETS'!X32 -> 265642
B18: OFFICE EQUIPMENT | D18: ='FIXED ASSETS'!X12 -> 4479 | F18: ='FIXED ASSETS'!X33 -> 525266
B19: COMPUTERS | D19: ='FIXED ASSETS'!X15 -> 27363 | F19: ='FIXED ASSETS'!X34 -> 451325
B20: GENERATOR | D20: ='FIXED ASSETS'!X16 -> 37550 | F20: ='FIXED ASSETS'!X35 -> 106532
B21: MOTOR VEHICLE | D21: ='FIXED ASSETS'!X17 -> 532276 | F21: ='FIXED ASSETS'!X36 -> 2417489
B22: MOTOR CYCLE | D22: ='FIXED ASSETS'!#REF! -> #REF! | F22: ='FIXED ASSETS'!X37 -> 70687
D23: =SUM(D17:D22) -> #REF! | F23: =SUM(F17:F22) -> 3836941
B25: NBV
B26: FURNITURE AND FIXTURES | D26: =D8-D17 -> 665000 | F26: =F8-F17 -> 56309
B27: OFFICE EQUIPMENT | D27: =D9-D18 -> 107949 | F27: =F9-F18 -> 195520
B28: COMPUTERS | D28: =D10-D19 -> 704637 | F28: =F10-F19 -> 21505
B29: GENERATOR | D29: =D11-D20 -> 1030450 | F29: =F11-F20 -> 48718
B30: MOTOR VEHICLE | D30: =D12-D21 -> 8248540 | F30: =F12-F21 -> 975186
B31: MOTOR CYCLE | D31: =D13-D22 -> #REF! | F31: =F13-F22 -> 2313
D32: =SUM(D26:D31) -> #REF! | F32: =SUM(F26:F31) -> 1299551
A38: Total | D38: =D32 -> #REF! | E38: =E32 -> 0 | F38: =F32 -> 1299551
A40: Long term deposits
A41: A/C Code | B41: Accounting Description | C41: R.F | D41: 2019 | E41: 2015 | F41: 2018
A43: 1020408 | B43: SECURITY DEPOSIT MOBILE | D43: ='Trial Combine 19'!I44 -> 0 | F43: 18500
A44: 1020409 | B44: SECURITY DEPOSIT OFFICE | D44: ='Trial Combine 19'!I45 -> 0 | F44: 192000
A45: 1020203 | B45: SECURITY DEPOSIT-PUMP | D45: ='Trial Combine 19'!I46 -> 0 | F45: 5000
A46: 1020206 | B46: SECURITY DEPOSIT (NESTLE) | D46: ='Trial Combine 19'!I47 -> 0 | F46: 1000
A58: Total | D58: =SUM(D42:D56) -> 0 | E58: =SUM(E42:E56) -> 0 | F58: =SUM(F42:F56) -> 216500
A60: CURRENT ASSETS
A61: A/C Code | B61: Accounting Description | C61: R.F | D61: =D41 -> 2019 | E61: 2015 | F61: =F41 -> 2018
B62: Trade debts - unsecured, considered good | D62: =D191 -> 0 | F62: =SOFP!#REF! -> #REF! | G62: =F62/E62 -> #REF!
B63: Due from related party | D63: =D212 -> 0 | F63: =SOFP!#REF! -> #REF!
B64: Advances, deposits, prepayments and other receivables | D64: =D241 -> -0.34 | F64: =SOFP!#REF! -> #REF!
B65: Tax refunds due from Government - income tax | D65: =SOFP!#REF! -> #REF! | F65: =SOFP!#REF! -> #REF!
B66: Cash and bank balances | D66: =D357 -> 8925 | F66: =SOFP!#REF! -> #REF!
A82: Total | D82: =SUM(D62:D80) -> #REF! | E82: =SUM(E62:E79) -> 0 | F82: =SUM(F62:F80) -> #REF!
A84: Trade debts - unsecured, considered good
A85: A/C Code | B85: Accounting Description | C85: R.F | D85: 2019 | E85: 2015 | F85: 2018
B87: Local
A89: 10301663 | B89: AGRO HUB INTERNATIONAL (PVT) LTD | D89: 0 | G89: 160564
B90: AHMED MANUFACTURING CORPORATION PVT LTD | D90: 0
A91: 10301267 | B91: AL GRETA SOLUTION | D91: ='Trial Combine 19'!I77 -> 0 | F91: 32114 | G91: 35991
B92: AKZO NOBEL PAKISTAN LIMITED | D92: 0 | F92: 93222
B93: AL-KARAM TEXTILE MILLS (PVT.)LTD. | D93: ='Trial Combine 19'!I78 -> 0 | F93: 37162
B94: Al RAHEEM TEXTILES INDUSTRIES | D94: ='Trial Combine 19'!I79 -> 0 | F94: 364404
B95: AL RAYAHEEN TRADING | F95: 68972
B96: ='Trial Combine 19'!B80 -> Ariston tradelinks | D96: ='Trial Combine 19'!I80 -> 0
A97: 10301582 | B97: ALSONS INDUSTRIES (PVT) LTD | D97: ='Trial Combine 19'!I84 -> 0 | F97: 168737 | G97: 37162
B98: ='Trial Combine 19'!B89 -> BASF PAKISTAN PVT LTD | D98: ='Trial Combine 19'!I89 -> 0
B99: ='[90]Trial Combine 18'!$B$81 -> BAZI KNITWEAR | D99: ='Trial Combine 19'!I90 -> 0 | F99: 32448
B100: BEAU ELITE PRODUCTS | F100: 3000
B101: ='Trial Combine 19'!B92 -> BIG BIRD FOOD PVT LTD | D101: ='Trial Combine 19'!I92 -> 0
B102: CHORUS LOGISTICS | F102: 1145
B103: CHOUDHRI INTERNATIONAL | F103: 244698
B104: CIROS ENTERPRISES | F104: 221496
B105: COMMANDINF OOFICER NAVAL | F105: 117866
B106: CHISTI ENTERPRISES | D106: 0
B107: ='Trial Combine 19'!B102 -> DAWOOD ENGINEERING PVT LTD | D107: ='Trial Combine 19'!I102 -> 0
B108: ='Trial Combine 19'!B103 -> DELTA INTERNATIONAL PVT LTD
B109: DRILLING SOLUTIONS PAKISTAN PRIVATE LIMITED | D109: ='Trial Combine 19'!I103 -> 0 | F109: 38500
A110: 10301265 | B110: EURO TEXTILES | D110: ='Trial Combine 19'!I106 -> 0 | F110: 350725
B111: EXIDE PAKISTAN LTD | D111: ='Trial Combine 19'!I107 -> 0
B112: FAD FASHION & DESIGN | D112: 0 | F112: 133316
B113: FIVE B SPORTING GOODS | F113: 33990
D114: 0
A115: 10301405 | B115: FINGER SOURCE CORPORATION | D115: ='Trial Combine 19'!I109 -> 0 | F115: 40338 | G115: 28475
B116: FUTURE TECHNOLOGIES | F116: 5000
A117: 10301675 | B117: GENERAL TRADING CORPORATION | D117: ='Trial Combine 19'!I113 -> 0 | F117: 40191 | G117: 3632
A118: 10301455 | B118: GLOBAL MARKETING CORPORATION | D118: 0 | F118: 17083
B119: GUL AHMED TEXTILE MILLS | D119: ='Trial Combine 19'!I115 -> 0
B120: GLOBAL EXPORTS | D120: 0
B121: GOODRICH MARITIME | D121: 0 | F121: 132110
A122: 10301583 | B122: H. SARDAR ALI AKHTAR ALI (PVT) LTD | D122: ='Trial Combine 19'!I118 -> 0 | F122: 1784379
B123: ='Trial Combine 19'!B120 -> HAFIZ TANNERY | D123: ='Trial Combine 19'!I120 -> 0
B124: HAKIM SONS PRIVATE LIMITED | F124: 5000
A125: 10301599 | B125: ISLAND TEXTILE MILLS LIMITED | D125: ='Trial Combine 19'!I126 -> 0 | F125: 133375 | G125: 350725
B126: ='Trial Combine 19'!B124 -> INNOVATIVE EQUIPMENT | D126: ='Trial Combine 19'!I124 -> 0
B127: ITTAHAD IMPEX | D127: ='Trial Combine 19'!I127 -> 0 | F127: 37200
B128: ='Trial Combine 19'!B125 -> INTERNATIONAL BUSINESS LINES | D128: ='Trial Combine 19'!I125 -> 0
A129: 10301578 | B129: KAPRAY | D129: 0 | G129: 166411.95
A130: 10301683 | B130: KASSIM TEXTILE PVT LTD | D130: ='Trial Combine 19'!I132 -> 0 | F130: 58321 | G130: 40191
B131: KAYSONS INTERNATIONAL PVT LTD | D131: ='Trial Combine 19'!I133 -> 0
A132: 10301392 | B132: KLTW TRADING CO | D132: ='Trial Combine 19'!I134 -> 0 | F132: 488318 | G132: 395350.34
B133: ='Trial Combine 19'!B135 -> L T ENGINEERING AND TRADE SERVICES | D133: ='Trial Combine 19'!I135 -> 0
B134: L.V.SHIPPING | D134: ='Trial Combine 19'!I136 -> 0 | F134: 246100
B135: LUCKY IMPEX | D135: ='Trial Combine 19'!I138 -> 0 | F135: 96300
B136: LINK BRIDGE | D136: ='Trial Combine 19'!I137 -> 0 | F136: 131770
A137: 1030143 | B137: M TAYYAB M TAHIR DYES | D137: ='Trial Combine 19'!I139 -> 0 | F137: 19000 | G137: 140937.8
A138: 1030196 | B138: MASF SHIPPING SERVICES | D138: ='Trial Combine 19'!I141 -> 0 | F138: 254991 | G138: 1033239.2
A139: 10301690 | B139: MEDISURE LABORATORIES PAKISTAN PVT LTD | D139: 0 | G139: 6360
B140: ='Trial Combine 19'!B146 -> MRS MOORAJ | D140: ='Trial Combine 19'!I146 -> 0
B141: ='Trial Combine 19'!B148 -> MS ZARMEE | D141: ='Trial Combine 19'!I148 -> 0
...

Sheet Win
E13: AIMAL KHAN TRADERS
A15: Audited Financial Statements
A16: FOR THE YEAR ENDED DECEMBER 31, 2025

Sheet SOFP
A1: =Win!E13 -> AIMAL KHAN TRADERS
A2: STATEMENT OF FINANCIAL POSITION
A3: AS AT DECEMBER 31, 2025
D5: 2025 | F5: 2024 | H5: 2023
C6: Note | D6: Rupees | F6: Rupees | H6: Rupees
A8: ASSETS
A10: NON CURRENT ASSETS
B12: FIXED ASSETS - NET | C12: 5 | D12: ='Note 5 ''2025'!J11 -> 6008090.4 | F12: ='Note 5'!J11 -> 6675656.4 | H12: ='Note 5'!J13 -> 7417396
B13: Deferred taxation | D13: 0 | F13: 0 | H13: 0
A15: CURRENT ASSETS
B17: Stores and spares | C17: =NOTES!A200 -> 6 | D17: =NOTES!L203 -> 85471121 | F17: =NOTES!N203 -> 57016539 | H17: =NOTES!P203 -> 48319101 | J17: 40948391 | L17: 57016539
B18: Trade receivables | C18: =NOTES!#REF!+1 -> #REF! | D18: =NOTES!#REF! -> #REF! | F18: =NOTES!#REF! -> #REF! | H18: =NOTES!#REF! -> #REF! | M18: =F18-H18 -> #REF! | N18: =M18/H18 -> #REF!
B19: Due from related parties | C19: =+NOTES!#REF!+1 -> #REF! | D19: =NOTES!#REF! -> #REF! | F19: =NOTES!#REF! -> #REF! | H19: =NOTES!#REF! -> #REF! | M19: =F19-H19 -> #REF! | N19: =M19/H19 -> #REF!
B20: Advances and prepayments | C20: =+NOTES!#REF!+1 -> #REF! | D20: =NOTES!#REF! -> #REF! | F20: =NOTES!#REF! -> #REF! | H20: =NOTES!#REF! -> #REF! | M20: =F20-H20 -> #REF! | N20: =M20/H20 -> #REF!
B21: Trade receivables | D21: 77671960 | F21: =83235575 -> 83235575 | H21: 66310392 | J21: 54801977 | L21: 80235575 | M21: =F21-H21 -> 16925183 | N21: =M21/H21 -> 0.25524179
B22: Advances, deposits & other receivables | C22: =NOTES!A207 -> 7 | D22: =NOTES!L213 -> 24183427 | F22: =NOTES!N213 -> 20467854 | H22: =NOTES!P213 -> 17323147 | J22: 14672931 | L22: 20467854
B23: Cash and bank balances | C23: =NOTES!A215 -> 8 | D23: =NOTES!L219 -> 85418833 | F23: =NOTES!N219 -> 61683695 | H23: =NOTES!P217 -> 13746153 | J23: 11608328 | L23: 17633772
D24: =D23+D22+D21+D17 -> 2.7274534e+08 | F24: =F21+F22+F23+F17 -> 222403663 | H24: =H21+H22+H23+H17+1 -> 145698794 | J24: =SUM(J17:J23) -> 122031627 | L24: =SUM(L17:L23) -> 175353740
A26: TOTAL ASSETS | D26: =D24+D12+1 -> 2.7875343e+08 | F26: =F24+F12+1 -> 2.2907932e+08 | H26: =H24+H12 -> 153116190
A29: CAPITAL AND LIABILITIES
B31: Authorized capital | D31: =G31 -> 0 | F31: =I31 -> 0 | H31: =J31 -> 0
B32: CAPITAL ACCOUNT
B34: Capital Account | C34: 9 | D34: =NOTES!L232 -> 1.9490692e+08 | F34: =NOTES!N232 -> 1.5258328e+08 | H34: =NOTES!P232 -> 129332833
D35: =SUM(D34) -> 1.9490692e+08 | F35: =SUM(F34) -> 1.5258328e+08 | H35: =SUM(H34) -> 129332833
A37: NON CURRENT LIABILITIES
B39: Long Term Loan - Bank Alfalah | C39: 10.1 | D39: =NOTES!L250 -> 4935850.2 | F39: =NOTES!N250 -> 9280373 | H39: 0
B40: Long Term Loan - Habib Bank Limited | C40: 10.2 | D40: =NOTES!L270 -> 30000000 | F40: =NOTES!N270 -> 30000000 | H40: 0
D41: =SUM(D39:D40) -> 34935850 | F41: =SUM(F39:F40) -> 39280373 | H41: =SUM(H39:H40) -> 0
B43: Deposit for purchase of shares | D43: ='Trial Combine 19'!$J$286 -> 0 | F43: ='Trial Combine 19'!$J$286 -> 0 | H43: ='Trial Combine 19'!$J$286 -> 0
B44: Deferred taxation | D44: ='Trial Combine 19'!$J$33 -> 0 | F44: ='Trial Combine 19'!$J$33 -> 0 | H44: ='Trial Combine 19'!$J$33 -> 0
B46: Deferred tax liabilities | D46: 0 | F46: 0 | H46: 0
D47: =D43+D46 -> 0 | F47: =F43+F46 -> 0 | H47: =H43+H46 -> 0
A48: CURRENT LIABILITIES
B50: Current Liability - Long term loan | C50: 10.1 | D50: =NOTES!L249 -> 4344522.8 | F50: =NOTES!N249 -> 4659066.7 | H50: 0
B51: Creditors, accrued expenses & other liabilities | C51: 11 | D51: =NOTES!L279 -> 44566142 | F51: =NOTES!N279 -> 32556604 | H51: =NOTES!P279 -> 23783357 | J51: 21713168
B52: Due to related party | C52: =+NOTES!#REF! -> #REF! | D52: 0 | F52: 0 | H52: 0
B54: Current portion of liabilities
B55: against asset subject to finance lease | C55: =+NOTES!#REF! -> #REF! | D55: =NOTES!#REF! -> #REF! | F55: =NOTES!#REF! -> #REF! | H55: =NOTES!#REF! -> #REF!
D56: =SUM(D50:D51) -> 48910665 | F56: =SUM(F50:F51) -> 37215671 | H56: =SUM(H50:H51) -> 23783357 | J56: =SUM(J51:J55) -> 21713168 | L56: =+H56-J56 -> 2070189
A58: CONTINGENCIES AND COMMITMENTS | C58: 16 | D58: 0 | F58: 0 | H58: 0
A60: TOTAL CAPITAL AND LIABILITIES | D60: =+D35+D41+D56+1 -> 2.7875343e+08 | F60: =+F35+F41+F56+1 -> 2.2907932e+08 | H60: =+H35+H39+H56 -> 153116190 | J60: =+F26-F60 -> 0.62999997
A62: The annexed notes form an integral part of these financial statements.
F72: PROPRIETOR
P221: =SUM(P220:P220) -> 0
C236: There was no contingent liability of the business at the terminal date - Nil (2023: Nil).
C238: There was no capital commitment of the business at the terminal date- Nil (2023: Nil).

Sheet CASH FLOW
A1: ='P & L'!A1 -> AIMAL KHAN TRADERS
A2: STATEMENT OF CASH FLOWS
A3: ='P & L'!A3 -> FOR THE YEAR ENDED DECEMBER 31, 2025
H5: ='P & L'!N5 -> 2023 | J5: ='P & L'!P5 -> 0
H6: Rupees | J6: Rupees
A8: CASH FLOW FROM OPERATING ACTIVITIES
A10: Profit/(loss) before taxation | H10: ='P & L'!N19 -> 76762135 | J10: ='P & L'!P19 -> 0
A11: Adjustment for non-cash and other items:
B12: Depreciation | H12: =-'FA-04'!L187 -> 1229125.1 | J12: 0
B13: Financial Charges | H13: =-'P & L'!#REF! -> #REF! | J13: =-'P & L'!#REF! -> #REF!
A14: Operating loss before working capital changes | H14: =H10+H12+H13 -> #REF! | J14: =J10+J12+J13 -> #REF!
A16: Net changes in working capital components:
A17: (Increase) / decrease in current assets
B18: =SOFP!B17 -> Stores and spares | H18: =SOFP!J17-SOFP!H17 -> -7370710 | J18: 0
B19: =SOFP!B22 -> Advances, deposits & other receivables | H19: =SOFP!J22-SOFP!H22 -> -2650216 | J19: 0
B20: Due from related parties | H20: 0 | J20: 0
B21: =SOFP!B21 -> Trade receivables | H21: =SOFP!J21-SOFP!H21 -> -11508415
A22: (Decrease) / increase in current liabilities
B23: =SOFP!B51 -> Creditors, accrued expenses & other liabilities | H23: =SOFP!H51-SOFP!J51 -> 2070189 | J23: 10000
C24: Due to related party | H24: =-SOFP!J52+SOFP!H52 -> 0 | J24: =-SOFP!#REF!+SOFP!J52 -> #REF!
H25: =ROUND(SUM(H18:H24),0) -> -19459152 | J25: =ROUND(SUM(J18:J24),0) -> #REF!
A26: Cash inflows from operating activities | H26: =H14+H25 -> #REF! | J26: =J14+J25 -> #REF!
B27: Income tax paid | H27: =-SOFP!J53 -> 0 | J27: 0
B28: Finance cost paid
B30: Financial charges paid | H30: ='P & L'!#REF! -> #REF! | J30: ='P & L'!#REF! -> #REF!
A31: Net cash generated from operating activities | H31: =H26+H27+H30 -> #REF! | J31: =J26+J27+J30 -> #REF!
A33: CASH FLOW FROM INVESTING ACTIVITIES
B34: Payments for Property, plant and equipment | H34: =-'FA-04'!L175 -> -9147966 | J34: 0
A36: Net cash (used in) from Investing activities | H36: =H34 -> -9147966 | J36: =J34 -> 0
A38: CASH FLOW FROM FINANCING ACTIVITIES
B39: Increase in paid up capital | H39: 0 | J39: 3000000
B40: =SOFP!#REF! -> #REF! | H40: =SOFP!#REF!-SOFP!#REF! -> #REF! | J40: 0
A41: NET INCREASE IN CASH AND CASH EQUIVALENTS | H41: =H31+H36+H39+H40 -> #REF! | J41: =J31+J36+J39+J40 -> #REF!
A43: CASH AND CASH EQUIVALENTS AT BEGINNING OF THE YEAR | H43: =J45 -> #REF! | J43: 0
A45: CASH AND CASH EQUIVALENTS AT END OF THE YEAR | G45: =NOTES!A215 -> 8 | H45: =H43+H369+H41 -> #REF! | J45: =J43+J369+J41 -> #REF!
A47: =+'P & L'!A33 -> The annexed notes form an integral part of these financial statements.
B53: =#REF! -> #REF! | J53: =#REF! -> #REF!
B54: =#REF! -> #REF! | J54: =#REF! -> #REF!
A55: SOFP | H55: =SOFP!H23 -> 13746153 | J55: =SOFP!J23 -> 11608328
A56: Difference | H56: =H45-H55 -> #REF! | J56: =J45-J55 -> #REF!

Sheet P & L
A1: =SOFP!A1 -> AIMAL KHAN TRADERS
A2: STATEMENT OF PROFIT OR LOSS
A3: =Win!A16 -> FOR THE YEAR ENDED DECEMBER 31, 2025
J5: 2025 | L5: 2024 | N5: =SOFP!H5 -> 2023
H6: Note | J6: Rupees | L6: Rupees | N6: Rupees
A8: Revenue- net | H8: 12 | J8: =NOTES!L282 -> 8.2445869e+08 | L8: =NOTES!N282 -> 732164323 | N8: =NOTES!P282 -> 650201889
A9: Cost of revenue | H9: 13 | J9: =-NOTES!L302 -> -6.7175285e+08 | L9: =-NOTES!N302 -> -6.1336297e+08 | N9: =-NOTES!P302 -> -545118808
A10: Gross Profit | J10: =SUM(J8:J9) -> 1.5270584e+08 | L10: =SUM(L8:L9) -> 1.1880135e+08 | N10: =SUM(N8:N9) -> 105083081
A12: OPERATING EXPENSES
A13: Administrative expenses | H13: 14 | J13: =NOTES!L318 -> 32608624 | L13: =NOTES!N318 -> 30396589 | N13: =NOTES!P318 -> 28312246
A14: Financial Charges | H14: 15 | J14: =NOTES!L337 -> 1327944.7 | L14: =NOTES!N337 -> 1061840.3 | N14: =NOTES!P337 -> 8700
J15: =SUM(J13:J14) -> 33936568 | L15: =SUM(L13:L14) -> 31458429 | N15: =SUM(N13:N14) -> 28320946
A16: OPERATING PROFIT FOR THE YEAR | J16: =+J10-J15 -> 1.1876927e+08 | L16: =+L10-L15 -> 87342920 | N16: =+N10-N15 -> 76762135
A18: Other Income | J18: 0 | L18: 0 | N18: 0
A19: Profit/(Loss) before taxation | J19: =+J16+J18 -> 1.1876927e+08 | L19: =+L16+L18 -> 87342920 | N19: =+N16+N18 -> 76762135
A21: Taxation | J21: =J19*0.13 -> 15440005 | L21: 10982465 | N21: 9753028
J22: 0 | L22: 0 | N22: 0
J23: ='Adj entry 19'!#REF! -> #REF! | L23: ='Adj entry 19'!#REF! -> #REF! | N23: ='Adj entry 19'!#REF! -> #REF!
J24: 0 | L24: 0 | N24: 0
J25: =SUM(J22:J24) -> #REF! | L25: =SUM(L22:L24) -> #REF! | N25: =SUM(N22:N24) -> #REF!
A27: Profit/(Loss) after taxation | J27: =J19-J21 -> 1.0332927e+08 | L27: =L19-L21 -> 76360455 | N27: =N19-N21 -> 67009107
A30: EARNINGS PER SHARE OF RS. 100 EACH -
B31: basic and diluted | H31: =+NOTES!#REF! -> #REF! | L31: =NOTES!#REF! -> #REF! | N31: =NOTES!#REF! -> #REF!
A33: =+SOFP!A62 -> The annexed notes form an integral part of these financial statements.
L51: =SOFP!F72 -> PROPRIETOR
B54: =SOFP!B71 -> 0
B55: =SOFP!B72 -> 0
Q78: 91381500
O79: 91381,500 3,600,000 500,000 800,000 709,300
O89: 800000
Q233: =SUM(Q232:Q232) -> 0
C249: There was no contingent liability of the business at the terminal date - Nil (2023: Nil).
C251: There was no capital commitment of the business at the terminal date- Nil (2023: Nil).

Sheet Cash Flows
A1: =SOFP!A1 -> AIMAL KHAN TRADERS
A2: STATEMENT OF CASH FLOW
A3: ='P & L'!A3 -> FOR THE YEAR ENDED DECEMBER 31, 2025
K5: 2025 | M5: 2024 | O5: 2023
K6: Rupees | M6: Rupees | O6: Rupees
A7: CASH FLOWS FROM OPERATING ACTIVITIES
B8: Profit/(Loss) before taxation | K8: ='P & L'!J27 -> 1.0332927e+08 | M8: ='P & L'!L27 -> 76360455 | O8: ='P & L'!N27 -> 67009107
A9: Adjustment for:
B11: Depreciation | K11: ='Note 5 ''2025'!H11 -> 667565.6 | M11: ='Note 5'!H11 -> 741739.6 | O11: ='Note 5'!H13 -> 824155
K12: =SUM(K11) -> 667565.6 | M12: =SUM(M11) -> 741739.6 | O12: =SUM(O11:O11) -> 824155
A13: Cash flow before working capital changes | K13: =+K8+K12 -> 1.0399683e+08 | M13: =+M8+M12 -> 77102195 | O13: =+O8+O12 -> 67833262
A14: Adjustment for working capital changes
B15: (Increase) / decrease in current assets
C16: Stores and spares | K16: =SOFP!F17-SOFP!D17 -> -28454582 | M16: =SOFP!H17-SOFP!F17 -> -8697438 | O16: =SOFP!J17-SOFP!H17 -> -7370710
C17: Trade receivables | K17: =SOFP!F21-SOFP!D21 -> 5563615 | M17: =SOFP!H21-SOFP!F21 -> -16925183 | O17: =SOFP!J21-SOFP!H21 -> -11508415
C18: Advances, deposits & other receivables | K18: =SOFP!F22-SOFP!D22 -> -3715572.5 | M18: =SOFP!H22-SOFP!F22 -> -3144707 | O18: =SOFP!J22-SOFP!H22 -> -2650216
K19: =SUM(K16:K18) -> -26606539 | M19: =SUM(M16:M18) -> -28767328 | O19: =SUM(O16:O18) -> -21529341
B20: Increase / (decrease) in current liabilities
C21: Current Liability | K21: =SOFP!D50-SOFP!F50 -> -314543.93 | M21: =SOFP!F50-SOFP!H50 -> 4659066.7 | O21: 0
C22: =SOFP!B51 -> Creditors, accrued expenses & other liabilities | K22: =-SOFP!F51+SOFP!D51 -> 12009538 | M22: =-SOFP!H51+SOFP!F51 -> 8773247 | O22: =SOFP!H51-SOFP!J51 -> 2070189
K23: =SUM(K21:K22) -> 11694994 | M23: =SUM(M21:M22) -> 13432314 | O23: =SUM(O21:O22) -> 2070189
C25: Drawings | K25: =NOTES!L231 -> -61005627 | M25: =NOTES!N231 -> -53110013 | O25: =NOTES!P231 -> -46236284
K26: =SUM(K25) -> -61005627 | M26: =SUM(M25) -> -53110013 | O26: =SUM(O25) -> -46236284
A28: Net cash generated from operating activities | K28: =+K13+K19+K23+K26 -> 28079661 | M28: =+M13+M19+M23+M26 -> 8657167.4 | O28: =+O13+O19+O23+O26 -> 2137826
A30: CASH FLOWS FROM INVESTING ACTIVITIES
B31: Purchase of property, plant and equipment | K31: 0 | M31: 0 | O31: 0
A32: Net cash generated from investing activities | K32: =SUM(K31:K31) -> 0 | M32: =SUM(M31:M31) -> 0 | O32: =SUM(O31:O31) -> 0
A34: CASH FLOWS FROM FINANCING ACTIVITIES
B35: Non Current Liability | K35: -4344523 | M35: =SOFP!F41 -> 39280373 | O35: 0
B36: Capital | K36: 0 | M36: 0 | O36: 0
A37: Net cash generated from financing activities | K37: =SUM(K35:K36) -> -4344523 | M37: =SUM(M35:M36) -> 39280373 | O37: =SUM(O35:O36) -> 0
A39: NET (DECREASE) / INCREASE IN CASH AND CASH EQUIVALENTS | K39: =+K28+K32+K37 -> 23735138 | M39: =+M28+M32+M37 -> 47937540 | O39: =+O28+O32+O37 -> 2137826
A40: CASH AND CASH EQUIVALENTS AT BEGINNING OF THE YEAR | K40: =M41 -> 61683695 | M40: =O41 -> 13746153 | O40: =SOFP!J23 -> 11608328
A41: CASH AND CASH EQUIVALENTS AT END OF THE YEAR | K41: =K39+K40 -> 85418833 | M41: =M39+M40+2 -> 61683695 | O41: =O39+O40-1 -> 13746153
A42: ='P & L'!A33 -> The annexed notes form an integral part of these financial statements.
M51: PROPRIETOR
P73: 91381500
N74: 91381,500 3,600,000 500,000 800,000 709,300
N84: 800000
P228: =SUM(P227:P227) -> 0

Sheet Policies FC
A2: ='P & L'!A1 -> AIMAL KHAN TRADERS
A3: NOTES TO THE FINANCIAL STATEMENTS
A4: ='P & L'!A3 -> FOR THE YEAR ENDED DECEMBER 31, 2025
A6: 1 | B6: FIRM AND ITS OPERATION
C8: Legal status and operations
C10: "M/S AIMAL KHAN TRADERS" is a registered business concern engaged in the business of Distribution of National Products in KPK.
A14: 2 | B14: STATEMENT OF COMPLIANCE | Q14: SIGNIFICANT ACCOUNTING POLICIES
C16: These financial statements have been prepared in accordance with the accounting and reporting standards as applicable in Pakistan. The accounting and reporting standards applicable in Pakistan comprise of:
C18: - | D18: Revised Accounting and Financial Reporting Standard for the Small -Sized Entities (Revised AFRS for SSEs) issued by the Institute of Chartered Accountants of Pakistan as notified under the Companies Act, 2017; and
C20: - | D20: Provisions of and directives issued under the Companies Act , 2017.
C22: Where provisions of and directives issued under the Companies Act, 2017 differ from the Revised AFRS for SSEs, the provisions of and directives issued under the Companies Act, 2017 have been followed.
A24: =A6+1 -> 2 | B24: 'BASIS OF PREPARATION
B26: =A24+0.1 -> 2.1 | C26: Statement of compliance
C28: These financial statements have been prepared in accordance with the accounting and financial reporting standards as applicable in Pakistan. The accounting and financial reporting standards as applicable in Pakistan comprise of:
B30: =B26+0.1 -> 2.2 | C30: Basis of measurement
C31: These financial statements have been prepared under the historical cost convention, except for certain items as disclosed in the relevant accounting policies below.
B33: =B30+0.1 -> 2.3 | C33: Functional and presentation currency
C35: These financial statements are presented in Pakistani Rupees which is also the firm’s functional currency. All financial information presented in Pakistani Rupees has been rounded to nearest rupee, unless otherwise indicated.
B37: =B33+0.1 -> 2.4 | C37: Key judgments, estimates and assumptions
C39: The preparation of financial statements in conformity with the accounting and reporting standards as applicable in Pakistan requires the use of certain critical accounting estimates. In addition, it requires management to exercise judgement in the process of applying the firm's accounting policies. The areas involving a high degree of judgement or complexity, or areas where assumptions and estimates are significant to the financial statements, are documented in the relevant accounting policies and notes.
C41: The revisions to ·accounting estimates (if any) are recognized in the period in which the estimate is revised i f the revision affects only that period or in the period of the revision and future periods if the revision affects both current and future periods.
C45: IAS-1 | E45: Presentation of Financial Statements – Presentation of items of other comprehensive income (Amendment)
C46: IAS-12 | E46: Income Taxes - Recovery of Underlying Assets (Amendment)
C48: The adoption of the above amendments did not have any material effect on these financial statements.
A49: =A24+1 -> 3 | B49: SUMMARY OF SIGNIFICANT ACCOUNTING POLICIES
C51: The significant accounting policies set out below have been applied consistently to all periods presented in these financial statements, unless otherwise stated.
C53: Deferred taxation is provided on all temporary timing differences by using the balance sheet method.
C55: Deferred income tax asset is recognized for all deductible temporary differences, carry-forward unused tax credits and unused tax losses, to the extent that it is probable that taxable profit will be available against which the deductible temporary differences, carry-forward of unused tax credits and unused tax losses can be utilized.
C57: Deferred tax liabilities are generally recognized for all taxable temporary differences .
C58: The carrying amount of deferred income tax assets is reviewed at each statement of financial position date and reduced to the extent that it is no longer probable that sufficient taxable profit will be available to allow all or part of the deferred income tax assets to be utilized.
C59: Deferred tax assets and liabilities are measured at the tax rates that are expected to apply to the period when the liability is settled based on tax rates that have been enacted or substantively enacted at the statement of financial position date.
B60: =#REF!+0.1 -> #REF! | C60: Staff retirement benefits | N60: 91381500
L61: 91381,500 3,600,000 500,000 800,000 709,300
C62: The firm operates un-recognized provident fund for its permanent employees. Equal monthly contribution by the employer and the employees at the rate of 5% of the basic salary is being made.
B64: =A49+0.1 -> 3.1 | C64: Property, plant and equipment
C68: o | D68: These are stated at cost less accumulated depreciation and impairment loss, if any.
C70: o | D70: Depreciation is calculated using reducing balance method at the rates stated in note 4. Depreciation charge commences from the month in which asset is available for use and continues until themonth of disposal.
L71: 800000
C72: o | D72: Useful lives, methods and rates of depreciation and residual values are reviewed and adjusted, if appropriate on regular basis. Any change in estimates in future years might affect the carrying amounts of the respective items of property, plant and equipment.
C73: =C72 -> o | D73: Normal repairs and maintenance is charged to revenue as and when incurred, while major renewals and replacements are capitalized.
C75: o | D75: Gains and losses on disposal of assets are recognized as an income or expense.
C77: o | D77: Assets under finance lease are stated at lower of present value of minimum lease payments under the lease agreement and the fair value of assets. Depreciation on these assets is charged according to firm's policies for similar assets.
C79: o | D79: The aggregate amount of obligations relating to assets subject to finance lease are accounted for at the net principal liability under the lease agreements.
C81: o | D81: Financial charges are allocated over the lease term so as to produce constant periodic rate of return on the outstanding principal liability for each period.
B83: =B64+0.1 -> 3.2 | C83: Intangible assets
C85: Intangible assets, other than goodwill, are measured at cost less accumulated amortization and accumulated impairment losses. Amortization is charged so as to allocate the cost of assets over their estimated useful lives, using the straight-line method at the rates specified in note 5 to the financial statements.
C87: Intangible assets,which are stated at cost less accamulated amortization and impairement losses, if any.
C91: All intangible assets are estimated to have definite useful lives and are amortized using straight line method at the applicable rates. Amortization on addition is charged for the full month in which these are purchased while no amortization is cahrged for the month in which the assets are disposed off.
B93: =B83+0.1 -> 3.3 | C93: Impairment
C95: The carrying amounts of the assets are reviewed at each balance sheet date to determine whether there is any indication of impairment loss. If any such indication exists the asset's recoverable amount is estimated in order to determine the extent of impairment loss, if any. Impairment losses are recognized in the profit and loss account.
C97: An impairment loss is reversed if there has been a change in the estimates used to determine the recoverable amount. An impairment loss is reversed only to the extent that the asset's carrying amount does not exceed the carrying amount that would have been determined , net of depreciation or amortization , if no impairment loss had been recognized.
B106: =B93+0.1 -> 3.4 | C106: Stores
C108: These are valued at cost using First -In-First-Out (FIFO) method.
B110: =B106+0.1 -> 3.5 | C110: Stock in trade
C111: These have been valued on the basis of lower of cost and net realizable value.
C112: Net realizable value signifies the selling price in the ordinary course of business less estimated costs of completion and selling expenses incidental thereto.
C113: Raw material | G113: - At moving average cost
C114: Finished goods | G114: - At moving average cost
B116: =B110+0.1 -> 3.6 | C116: Trade debts
C117: Trade debts are carried at original invoice amount less an estimate made for doubtful receivables, if any, based on a review of all outstanding amounts at the year end. Bad debts are written off when identified.
B120: =B116+0.1 -> 3.7 | C120: Cash & cash equivalents | Q120: =175-35.01+90 -> 229.99
Q121: =Q120/22 -> 10.454091
C122: Cash and cash equivalents are carried at cost in the statement of financial position. For the purpose of cash flows, cash and cash equivalents comprises cash in hand and cash at banks.
B124: =B120+0.1 -> 3.8 | C124: Trade and other payables
C126: Liabilities for trade and other payables are carried at cost which is the fair value of the consideration to be paid in future for goods and services received.
B127: =B124+0.1 -> 3.9 | C127: Trade and other receivables
C129: Trade and other receivables are recognized at transaction price less an allowance for impairment.
C130: A provision for impairment of trade receivables is established when there is objective evidence that the firm will not be able to collect all amounts due according to the original terms of the receivables. The amount of the provision is recognized in the statement of profit or loss. Bad debts are written-off in the statement of profit or loss on identification.
B133: 3.09 | C133: Staff retirement benefits
C135: The firm does not operate any staff retirement benefit scheme.
B137: =B133+0.01 -> 3.1 | C137: Provision
C139: A provision is recognized in the statement of financial position of the firm when the firm has a legal or constructive obligation as a result of a past event; and it is probable that an outflow of economic resources embodying economic benefit will be required to settle the obligation and a reliable estimate can be made of the amount of obligation. However, the provisions are adjusted at each reporting period to reflect the best estimate.
B140: =B137+0.01 -> 3.11 | C140: Taxation
C142: Provision for current taxation is based on taxable income at the current rates of taxation after taking into account applicable tax credits, rebates and exemptions, if any.
B145: =B140+0.01 -> 3.12 | C145: Foreign currency transactions
C147: Transactions in foreign currencies are converted into Pak rupees at the rate of exchange prevailing on the date of transaction. Monetary assets and liabilities in foreign currencies are translated into Pak rupees at the rates of exchange prevailing at the balance sheet date. Exchange gains and losses are includedin current year's income.
A151: 4 | C151: Revenue recognition
C153: Contract revenue is recognised when goods are dispatched and ownership risk and rewards are transferred to the buyer.
N233: =SUM(N232:N232) -> 0
C249: There was no contingent liability of the business at the terminal date - Nil (2023: Nil).
C251: There was no capital commitment of the business at the terminal date- Nil (2023: Nil).
N278: 2013120

Sheet FA-04
A2: 4 | B2: PROPERTY AND EQUIPMENT- Tangible | D2: 2021 | F2: 2020
D3: Rupees | F3: Rupees
B5: Property and equipments (Note 4.1) | D5: =L195 -> 7918840.9 | F5: 850000
A8: =A2+0.1 -> 4.1 | B8: Reconciliation of carrying amounts at the beginning and end of the year is as follows:
D10: Owned | J10: Leased | L10: Total
D11: Land & Building | F11: Furniture & Fixtures | H11: Plant & Machinery | J11: Vehicles
D12: ------------------------------------------------------------------- Rupees ----------------------------------------------------------------------
B13: Year ended 30 June 2011
B14: Opening net book value | D14: 31563 | F14: 9879 | G14: 0 | H14: 48719 | L14: 44127890
B15: Additions | D15: 0 | F15: 0 | H15: 243958 | L15: 72132365
B16: Transfers | D16: 0 | F16: 0 | H16: 0 | L16: -1456875
B17: Adjustments | D17: 0 | F17: 0 | H17: 0 | L17: 0
B18: Disposal (at NBV) | D18: 0 | F18: 0 | H18: 0 | L18: 0
L19: 0
B20: Depreciation | D20: -4735 | F20: -1482 | H20: -18635 | L20: -14559477
D21: 26828 | F21: 8397 | G21: 0 | H21: 274042 | L21: 100243903
B22: Closing net book value
B24: At 30 June 2011
B25: Cost | D25: 34850 | F25: 12557 | G25: 0 | H25: 308958 | L25: 125912076
B26: Accumulated depreciation | D26: -8022 | F26: -4160 | G26: 0 | H26: -34916 | L26: -25668173
B27: Net book value | D27: 26828 | F27: 8397 | H27: 274042 | L27: 100243903
B29: Year ended 30 June 2012
B30: Opening net book value | D30: 26828 | F30: 8397 | G30: 0 | H30: 274042 | L30: =SUM(D30:H30) -> 309267
B31: Additions | D31: 0 | F31: 0 | H31: 742593 | L31: =SUM(D31:H31) -> 742593
B33: Depreciation | D33: -4024.2 | F33: -1259.55 | H33: -65217 | L33: -17337122
B35: Closing net book value | D35: =D30+D31+D33 -> 22803.8 | F35: =F30+F31+F33 -> 7137.45 | H35: =H30+H31+H33 -> 951418 | L35: =L30+L31+L33 -> -16285262
B37: At 30 June 2012
B39: Cost | D39: 34850 | F39: 12557 | G39: 0 | H39: 1051551 | L39: =SUM(D39:H39) -> 1098958
B40: Accumulated depreciation | D40: -12046.2 | F40: -5419.55 | G40: 0 | H40: -100133 | L40: =SUM(D40:H40) -> -117598.75
B41: Net book value | D41: =SUM(D39:D40) -> 22803.8 | F41: =SUM(F39:F40) -> 7137.45 | H41: =SUM(H39:H40) -> 951418 | L41: =SUM(L39:L40) -> 981359.25
B43: Year ended 30 June 2013
B44: Opening net book value | D44: =+D41 -> 22803.8 | F44: =+F41 -> 7137.45 | G44: 0 | H44: =+H41 -> 951418 | L44: =SUM(D44:H44) -> 981359.25
B45: Additions | D45: 28854 | F45: 0 | H45: 683430 | L45: =SUM(D45:H45) -> 712284
B47: Depreciation | D47: -7749 | F47: -1070 | H47: -175678 | L47: =SUM(D47:H47) -> -184497
B49: Closing net book value | D49: =SUM(D44:D47) -> 43908.8 | F49: =SUM(F44:F47) -> 6067.45 | H49: =SUM(H44:H47) -> 1459170 | L49: =SUM(L44:L47) -> 1509146.2
B51: At 30 June 2013
B53: Cost | D53: =D39+D45 -> 63704 | F53: =F39+F45 -> 12557 | G53: 0 | H53: =H39+H45 -> 1734981 | L53: =SUM(D53:H53) -> 1811242
B54: Accumulated depreciation | D54: =+D40+D47 -> -19795.2 | F54: =+F40+F47 -> -6489.55 | G54: 0 | H54: =+H40+H47 -> -275811 | L54: =SUM(D54:H54) -> -302095.75
B55: Net book value | D55: =SUM(D53:D54) -> 43908.8 | F55: =SUM(F53:F54) -> 6067.45 | H55: =SUM(H53:H54) -> 1459170 | L55: =SUM(L53:L54) -> 1509146.2
B57: Year ended 30 June 2014
B58: Opening net book value | D58: =+D55 -> 43908.8 | F58: =+F55 -> 6067.45 | H58: =+H55 -> 1459170 | J58: 0 | L58: =SUM(D58:J58) -> 1509146.2
B59: Additions | D59: 0 | F59: 0 | H59: 926407 | J59: 0 | L59: =SUM(D59:J59) -> 926407
B61: Depreciation | D61: -6586 | F61: -910 | H61: -230456 | J61: 0 | L61: =SUM(D61:J61) -> -237952
B63: Closing net book value | D63: =D58+D59+D61 -> 37322.8 | F63: =F58+F59+F61 -> 5157.45 | H63: =H58+H59+H61 -> 2155121 | J63: =J58+J59+J61 -> 0 | L63: =L58+L59+L61 -> 2197601.2
B65: At 30 June 2014
B67: Cost | D67: =+D53+D59 -> 63704 | F67: =+F53+F59 -> 12557 | H67: =+H53+H59 -> 2661388 | J67: 0 | L67: =SUM(D67:J67) -> 2737649
B68: Accumulated depreciation | D68: =+D54+D61+0.2 -> -26381 | F68: =+F54+F61-0.45 -> -7400 | H68: =+H54+H61 -> -506267 | J68: 0 | L68: =SUM(D68:J68) -> -540048
B69: Net book value | D69: =SUM(D67:D68) -> 37323 | F69: =SUM(F67:F68) -> 5157 | H69: =SUM(H67:H68) -> 2155121 | I69: =SUM(I67:I68) -> 0 | J69: =SUM(J67:J68) -> 0 | L69: =SUM(L67:L68) -> 2197601
B71: Year ended 30 June 2015
B72: Opening net book value | D72: =+D69 -> 37323 | F72: =+F69 -> 5157 | H72: =+H69 -> 2155121 | J72: 0 | L72: =SUM(D72:J72) -> 2197601
B73: Additions | D73: 23900 | F73: 0 | H73: 286423 | J73: 0 | L73: =SUM(D73:J73) -> 310323
B74: Disposal
B75: Cost | D75: 0 | F75: 0 | H75: 0 | J75: 0 | L75: =SUM(D75:J75) -> 0
B76: Accumulated depreciation | D76: 0 | F76: 0 | H76: 0 | J76: 0 | L76: =SUM(D76:J76) -> 0
B77: Net book value-(disposal) | D77: =SUM(D75:D76) -> 0 | F77: =SUM(F75:F76) -> 0 | H77: =SUM(H75:H76) -> 0 | J77: =SUM(J75:J76) -> 0 | L77: =-SUM(L75:L76) -> 0
B79: Depreciation | D79: -6793 | F79: -773 | H79: -326849 | J79: 0 | L79: =SUM(D79:J79) -> -334415
B81: Closing net book value | D81: =D72+D73+D79 -> 54430 | F81: =F72+F73+F79 -> 4384 | H81: =H72+H73+H79 -> 2114695 | J81: =J72+J73+J79 -> 0 | L81: =L72+L73+L79+L77 -> 2173509
B83: At 30 June 2015
B85: Cost | D85: =+D67+D73 -> 87604 | F85: =+F67+F73 -> 12557 | H85: =+H67+H73 -> 2947811 | J85: 0 | L85: =SUM(D85:J85) -> 3047972
B86: Accumulated depreciation | D86: =+D68+D79 -> -33174 | F86: =+F68+F79 -> -8173 | H86: =+H68+H79 -> -833116 | J86: 0 | L86: =SUM(D86:J86) -> -874463
B88: Net book value | D88: =SUM(D85:D86) -> 54430 | F88: =SUM(F85:F86) -> 4384 | H88: =SUM(H85:H86) -> 2114695 | J88: =SUM(J85:J86) -> 0 | L88: =SUM(L85:L86) -> 2173509
B90: Year ended 30 June 2016
B91: Opening net book value | D91: =D88 -> 54430 | F91: =F88 -> 4384 | H91: =H88 -> 2114695 | J91: =J88 -> 0 | L91: =SUM(D91:J91) -> 2173509
B92: Additions | D92: =+'[96]FA-Working 15-16'!D15 -> 0 | F92: =+'[96]FA-Working 15-16'!D17 -> 0 | H92: =+'[96]FA-Working 15-16'!D19 -> 67016 | J92: =+'[96]FA-Working 15-16'!D29 -> 9994072 | L92: =SUM(D92:J92) -> 10061088
B94: Disposal
B95: Cost | D95: 0 | F95: 0 | H95: 0 | J95: 0 | L95: =SUM(D95:J95) -> 0
B96: Accumulated depreciation | D96: 0 | F96: 0 | H96: 0 | J96: 0 | L96: =SUM(D96:J96) -> 0
B97: Net book value-(disposal) | D97: =D95-D96 -> 0 | F97: =F95-F96 -> 0 | H97: =H95-H96 -> 0 | J97: =J95-J96 -> 0 | L97: =L95-L96 -> 0
B99: Depreciation | D99: =-'[96]FA-Working 15-16'!H15 -> -8164.4325 | F99: =-'[96]FA-Working 15-16'!H17 -> -657.39 | H99: =-'[96]FA-Working 15-16'!H19 -> -319717.56 | J99: =-'[96]FA-Working 15-16'!H29 -> -1249259 | L99: =SUM(D99:J99) -> -1577798.4
B101: Closing net book value | D101: =D91+D92+D99-D97 -> 46265.567 | F101: =F91+F92+F99-F97 -> 3726.61 | H101: =H91+H92+H99-H97 -> 1861993.4 | J101: =J91+J92+J99-J97 -> 8744813 | L101: =L91+L92+L99-L97 -> 10656799
B103: At 30 June 2016
B105: Cost | D105: =D85+D92 -> 87604 | F105: =F85+F92 -> 12557 | H105: =H85+H92 -> 3014827 | J105: =J85+J92 -> 9994072 | L105: =SUM(D105:J105) -> 13109060
B106: Accumulated depreciation | D106: =D86+D99 -> -41338.433 | F106: =F86+F99 -> -8830.39 | H106: =H86+H99 -> -1152833.6 | J106: =J86+J99 -> -1249259 | L106: =SUM(D106:J106) -> -2452261.4
B108: Net book value | D108: =D105+D106 -> 46265.567 | F108: =F105+F106 -> 3726.61 | H108: =H105+H106 -> 1861993.4 | J108: =J105+J106 -> 8744813 | L108: =L105+L106 -> 10656799
B110: Year ended 30 June 2017
B111: Opening net book value | D111: =D108 -> 46265.567 | F111: =F108 -> 3726.61 | H111: =H108 -> 1861993.4 | J111: =J108 -> 8744813 | L111: =SUM(D111:J111)-0.46 -> 10656798
B112: Additions | D112: ='[96]FAS - Working 16-17'!D15 -> 0 | F112: ='[96]FAS - Working 16-17'!D17 -> 0 | H112: ='[96]FAS - Working 16-17'!D19 -> 438203 | J112: ='[96]FAS - Working 16-17'!D29 -> 0 | L112: =SUM(D112:J112) -> 438203
B114: Disposal
B115: Cost | D115: 0 | F115: 0 | H115: 0 | J115: 0 | L115: =SUM(D115:J115)-0.4 -> -0.4
B116: Accumulated depreciation | D116: 0 | F116: 0 | H116: 0 | J116: 0 | L116: =SUM(D116:J116)-0.18 -> -0.18
B117: Net book value-(disposal) | D117: =D115-D116 -> 0 | F117: =F115-F116 -> 0 | H117: =H115-H116 -> 0 | J117: =J115-J116 -> 0 | L117: =L115+L116 -> -0.58
B119: Depreciation | D119: =-'[96]FAS - Working 16-17'!H15-0.23 -> -6939.9976 | F119: =-'[96]FAS - Working 16-17'!H17-0.22 -> -559.0015 | H119: =-'[96]FAS - Working 16-17'!H19-0.43 -> -312669 | J119: =-'[96]FAS - Working 16-17'!H29-0.05 -> -1311722 | L119: =SUM(D119:J119) -> -1631890
B121: Closing net book value | D121: =D111+D112-D117+D119 -> 39325.57 | F121: =F111+F112-F117+F119 -> 3167.6085 | H121: =H111+H112-H117+H119 -> 1987527.4 | J121: =J111+J112-J117+J119 -> 7433091 | L121: =L111+L112-L117+L119 -> 9463111.7
B123: At 30 June 2017
B125: Cost | D125: =D105+D112-D115 -> 87604 | F125: =F105+F112-F115 -> 12557 | H125: =H105+H112-H115 -> 3453030 | J125: =J105+J112-J115 -> 9994072 | L125: =SUM(D125:J125)+0.4 -> 13547263
B126: Accumulated depreciation | D126: =D106-D116+D119+0.43 -> -48278 | F126: =F106-F116+F119+0.39 -> -9389.0015 | H126: =H106-H116+H119-0.44 -> -1465503 | J126: =J106-J116+J119 -> -2560981 | L126: =SUM(D126:J126) -> -4084151
B128: Net book value | D128: =D125+D126 -> 39326 | F128: =F125+F126 -> 3167.9985 | H128: =H125+H126 -> 1987527 | J128: =J125+J126 -> 7433091 | L128: =L125+L126 -> 9463112.4
B130: Year ended 30 June 2019
B131: Opening net book value | D131: 0 | F131: 0 | H131: 0 | J131: 0 | L131: =SUM(D131:J131) -> 0
B132: Additions | D132: ='FIXED ASSETS'!K11 -> 700000 | F132: ='FIXED ASSETS'!K12 -> 112428 | H132: ='FIXED ASSETS'!K13 -> 359358 | J132: 0 | L132: =SUM(D132:J132) -> 1171786
B134: Disposal/Transfer to IAS-40
B135: Cost | D135: 0 | F135: 0 | H135: 0 | J135: 0 | L135: =SUM(D135:J135) -> 0
B136: Accumulated depreciation | D136: 0 | F136: 0 | H136: 0 | J136: 0 | L136: =SUM(D136:J136) -> 0
B137: Net book value-(disposal/transfer) | D137: =D136+D135 -> 0 | F137: =F136+F135 -> 0 | H137: =H136+H135 -> 0 | J137: =J136+J135 -> 0 | L137: =L136+L135 -> 0
B139: Depreciation | D139: -35000 | F139: -4479 | H139: -61441 | J139: 0 | L139: =SUM(D139:J139) -> -100920
B141: Closing net book value | D141: =D131+D132-D137+D139 -> 665000 | F141: =F131+F132-F137+F139 -> 107949 | H141: =H131+H132-H137+H139 -> 297917 | J141: =J131+J132-J137+J139 -> 0 | L141: =L131+L132-L137+L139 -> 1070866
B143: At 30 June 2019
B145: Cost | D145: =D131+D132 -> 700000 | F145: =F131+F132 -> 112428 | H145: =H131+H132 -> 359358 | J145: 0 | L145: =SUM(D145:H145) -> 1171786
B146: Accumulated depreciation | D146: =D139 -> -35000 | F146: =F139 -> -4479 | H146: =H139 -> -61441 | J146: 0 | L146: =SUM(D146:H146) -> -100920
B147: Net book value | D147: =D145+D146 -> 665000 | F147: =F145+F146 -> 107949 | H147: =H145+H146 -> 297917 | J147: =J145+J146 -> 0 | L147: =L145+L146 -> 1070866
...

Sheet Note 5 '2025
A1: 5 | B1: FIXED ASSETS
B3: PARTICULARS | C3: COST | F3: Rate% | G3: DEPRECIATION | J3: W.D.V As at 31/12/2025
C4: As at 1/1/2025 | D4: Additions / Deletions | E4: As at 31/12/2025 | G4: As at 1/1/2025 | H4: For the Year | I4: As at 31/12/2025
B6: Office Decoration | C6: 1503162 | D6: 0 | E6: =+C6+D6 -> 1503162 | F6: 0.1 | G6: 704320 | H6: =(E6-G6)*0.1 -> 79884.2 | I6: =+G6+H6 -> 784204.2 | J6: =+E6-I6 -> 718957.8
B7: Motor Vehicles | C7: 9469948 | E7: =+C7+D7 -> 9469948 | F7: 0.1 | G7: 3943332 | H7: =(E7-G7)*0.1 -> 552661.6 | I7: =+G7+H7 -> 4495993.6 | J7: =+E7-I7 -> 4973954.4
B8: Furniture & Fixtures | C8: 354122 | D8: 0 | E8: =+C8+D8 -> 354122 | F8: 0.1 | G8: 141232 | H8: =(E8-G8)*0.1 -> 21289 | I8: =+G8+H8 -> 162521 | J8: =+E8-I8 -> 191601
B9: Computer & Electric Equipments | C9: 192550 | E9: =+C9+D9 -> 192550 | F9: 0.1 | G9: 90229 | H9: =(E9-G9)*0.1 -> 10232.1 | I9: =+G9+H9 -> 100461.1 | J9: =+E9-I9 -> 92088.9
B10: Other Assets | C10: 65835 | D10: 0 | E10: =+C10+D10 -> 65835 | F10: 0.1 | G10: 30848 | H10: =(E10-G10)*0.1 -> 3498.7 | I10: =+G10+H10 -> 34346.7 | J10: =+E10-I10 -> 31488.3
B11: 2025 | C11: =SUM(C6:C10) -> 11585617 | D11: =SUM(D6:D10) -> 0 | E11: =SUM(E6:E10) -> 11585617 | G11: =SUM(G6:G10) -> 4909961 | H11: =SUM(H6:H10) -> 667565.6 | I11: =SUM(I6:I10) -> 5577526.6 | J11: =SUM(J6:J10) -> 6008090.4
B13: 2024 | C13: =+C11 -> 11585617 | E13: =+C13 -> 11585617 | G13: 4168221 | H13: 741740 | I13: =+G13+H13 -> 4909961 | J13: =+C13-I13 -> 6675656
A15: 5.1 | B15: Deprecation for the year has been allocated as under:
G16: 2025 | H16: 2024
G17: Rupees | H17: Rupees
D18: Cost of Sales | G18: =H11*0.8 -> 534052.48 | H18: =H13*0.8 -> 593392
D19: Operating Expenses | G19: =H11*0.2 -> 133513.12 | H19: =H13*0.2 -> 148348
G20: =SUM(G18:G19) -> 667565.6 | H20: =SUM(H18:H19) -> 741740

Sheet NOTES
A1: =SOFP!A1 -> AIMAL KHAN TRADERS
A2: ='Policies FC'!A3:N3 -> NOTES TO THE FINANCIAL STATEMENTS
A3: ='Policies FC'!A4 -> FOR THE YEAR ENDED DECEMBER 31, 2025
A5: 1 | B5: COMPANY AND ITS OPERATION
C7: Legal status and operations
C9: Food Caravan (Pvt) Limited was incorporated in Pakistan on October 5, 2018 under the Companies Act, 2017 on May 30, 2017 as a private company limited by shares and is engaged in the business of provision of food. The registered office of the company is situated at 435K-Block Model town Lahore, whereas the location of principal place of its business is situated at CCA 237, Sector FF, Phase IV Commercial, DHA, Lahore.
B11: =B7+0.1 -> 0.1 | C11: Summary of significant events and transactions in the current reporting period.
C13: The Third and Fifth Schedules to the Companies Act, 2017 became applicable to the Company for the first time for the preparation of these financial statements. The Companies Act, 2017 (including its Third and Fifth Schedule) forms an integral part of the statutory financial reporting framework applicable to the Company and amongst others, prescribes the nature and content of disclosures in relation to various elements of the financial statements. Additional disclosures include but are not limited to, additional disclosure requirements for related parties (refer note 21) and management assessment of sufficiency of tax provision in the financial statements (refer note 18), etc.
A15: 2 | B15: STATEMENT OF COMPLIANCE
C17: These financial statements have been prepared in accordance with the accounting and reporting standards as applicable in Pakistan. The accounting and reporting standards applicable in Pakistan comprise of:
C19: - | D19: Revised Accounting and Financial Reporting Standard for the Small -Sized Entities (Revised AFRS for SSEs) issued by the Institute of Chartered Accountants of Pakistan as notified under the Companies Act, 2017; and
C21: - | D21: Provisions of and directives issued under the Companies Act , 2017.
C23: Where provisions of and directives issued under the Companies Act, 2017 differ from the Revised AFRS for SSEs, the provisions of and directives issued under the Companies Act, 2017 have been followed.
A25: =A5+1 -> 2 | B25: BASIS OF PREPARATION
B27: =A25+0.1 -> 2.1 | C27: Accounting convention
C29: These financial statements have been prepared under the historical cost convention without any adjustment for inflation or current values. In these financial statements, except for cash flow statement, all the transactions have been accounted for on accrual basis.
B31: =B27+0.1 -> 2.2 | C31: Functional and presentation currency
B35: =B31+0.1 -> 2.3 | C35: Key judgments, estimates and assumptions
C37: The preparation of financial statements in conformity with Revised AFRS for SSEs requires management to make judgments, estimates and assumptions that affect the application of policies and reported amounts of assets and liabilities, income and expenses. The estimates and associated assumptions are based on historical experience and various other factors that are believed to be reasonable under the circumstances, the results of which form the basis of making the judgments about carrying values of assets and liabilities that are not readily apparent from other sources. Actual results may differ from these estimates.
C39: The estimates and underline assumptions are reviewed on an on going basis. Revisions to accounting estimates are recognized in the period in which the estimates are revised.
C42: Significant areas requiring the use of the management estimates in these financial statements relates to the useful lives and residual values of the property, plant and equipment, provision for doubtful debts on account receivables, estimation of contingencies, and estimation of taxation. However, assumptions and judgments made by management in the application of accounting policies that have significant effect on the financial statements are not expected to result in material adjustment to the carrying amounts of assets and liabilities in the next year.
C48: IAS-1 | E48: Presentation of Financial Statements – Presentation of items of other comprehensive income (Amendment)
C49: IAS-12 | E49: Income Taxes - Recovery of Underlying Assets (Amendment)
C51: The adoption of the above amendments did not have any material effect on these financial statements.
A52: =A25+1 -> 3 | B52: SUMMARY OF SIGNIFICANT ACCOUNTING POLICIES
B54: The significant accounting policies set out below have been applied consistently to all periods presented in these financial statements, unless otherwise stated.
B56: =A52+0.1 -> 3.1 | C56: Taxation
C58: Current
C60: The current taxation is computed on the basis of profit for the year adjusted for fiscal purposes after taking into account the tax credit or rebate, if any or Alternative Corporate Tax @ 17% of accounting income u/s 113 C of the Income Tax Ordinance, 2001 or minimum tax u/s 113 of the Income Tax Ordinance, 2001, whichever is higher.
C62: Deferred | P62: 91381500
N63: 91381,500 3,600,000 500,000 800,000 709,300
C64: The accounting standards applicable to size and stature of the company do not require the recognition of deferred tax. Accordingly deferred tax (asset)/liability is not recognized in these financial statements being not applicable in the instant case.
C65: Deferred taxation is provided on all temporary timing differences by using the balance sheet method.
C67: Deferred income tax asset is recognized for all deductible temporary differences, carry-forward unused tax credits and unused tax losses, to the extent that it is probable that taxable profit will be available against which the deductible temporary differences, carry-forward of unused tax credits and unused tax losses can be utilized.
C69: Deferred tax liabilities are generally recognized for all taxable temporary differences .
C70: The carrying amount of deferred income tax assets is reviewed at each statement of financial position date and reduced to the extent that it is no longer probable that sufficient taxable profit will be available to allow all or part of the deferred income tax assets to be utilized.
C71: Deferred tax assets and liabilities are measured at the tax rates that are expected to apply to the period when the liability is settled based on tax rates that have been enacted or substantively enacted at the statement of financial position date.
N72: 500000
B73: =B56+0.1 -> 3.2 | C73: Staff retirement benefits | N73: 800000
N74: 709300
C75: The company operates un-recognized provident fund for its permanent employees. Equal monthly contribution by the employer and the employees at the rate of 5% of the basic salary is being made.
B77: =B56+0.1 -> 3.2 | C77: Property, plant and equipment
C81: o | D81: These are stated at cost less accumulated depreciation and impairment loss, if any.
C83: o | D83: Depreciation is charged to income by applying the reducing balance method at the rates specified in note 5, considering the useful lives of these assets and after taking into account that no depreciation is provided on assets in the month in which these are sold while charge for the full month is made in which these are purchased.
C85: o | D85: Minor renewals, replacements, maintenance and repairs are expensed. Major renewals and betterments are capitalized.
C87: o | D87: Gains and losses on deleted assets are recognized as an income or expense.
C89: o | D89: Assets under finance lease are stated at lower of present value of minimum lease payments under the lease agreement and the fair value of assets. Depreciation on these assets is charged according to company's policies for similar assets.
C91: o | D91: The aggregate amount of obligations relating to assets subject to finance lease are accounted for at the net principal liability under the lease agreements.
C93: o | D93: Financial charges are allocated over the lease term so as to produce constant periodic rate of return on the outstanding principal liability for each period.
B95: =B77+0.1 -> 3.3 | C95: Intangible assets
C97: Initial Recognition
C99: Intangible assets, other than goodwill, are measured at cost less accumulated amortization and accumulated impairment losses. Amortization is charged so as to allocate the cost of assets over their estimated useful lives, using the straight-line method at the rates specified in note 5 to the financial statements.
C101: Intangible assets, which are stated at cost less accumulated amortization and impairment losses, if any, represent the cost of software. Cost associated with maintaining these assets are charged to the statement of comprehensive incomes and when incurred, however, cost that directly attributable to the identifiable asset and have probable economic benefits exceeding one year, are recognized as intangible assets.
C105: All intangible assets are estimated to have definite useful lives and are amortized using straight line method over period of 3 years. Amortization on addition is charged for the full month in which these are purchased while no amortization is charged for the month in which the assets are disposed off.
C107: Judgment and estimates
C109: The useful lives, residual values and amortization method are reviewed on a regular basis. The effect of any changes in estimate accounted for on a prospective basis.
C111: The property & equipment and intangible assets 'residual value and useful lives are reviewed, and adjusted if appropriate, at each financial year end. The effect of any adjustment to residual values and useful lives is recognized prospectively as a change in accounting estimate.
B114: =B95+0.1 -> 3.4 | C114: Impairment of non-financial assets
C116: The assets that are subject to depreciation or amortization are assessed at each reporting date to determine whether there is any indication that the assets are impaired. If there is an indication of possible impairment, the recoverable amount of the asset is estimated and compared with its carrying amount.
C118: An impairment loss is recognized if the carrying amount of an asset exceeds its estimated recoverable amount. The impairment loss is recognized in the statement of profit or loss, unless the relevant asset is carried at a revalued amount, in which case the impairment loss is treated as a revaluation decrease.
C120: An impairment loss is reversed only to the extent that the asset carrying amount does not exceed the carrying amount that would have been determined, net of depreciation or amortization, if no impairment loss had been recognized. The Company recognizes the reversal immediately in the statement of profit or loss, unless the asset is carried at a revalued amount in accordance with the revaluation model. Any reversal of an impairment loss of a revalued asset is treated as a revaluation increase.
B122: =B114+0.1 -> 3.5 | C122: Impairment of financial assets other than trade receivables
C124: The financial assets other than those that are carried at fair value are assessed at each reporting date to determine whether there is any objective evidence of their impairment. A financial asset is impaired if there is objective evidence of impairment as a result of one or more events that occurred after the initial recognition of the asset, and that loss event(s) had an impact on the estimated future cash flows of that asset that can be estimated reliably.
C126: The impairment loss is recognized immediately in the statement of profit or loss and the carrying amount of the related financial asset is reduced accordingly. An impairment loss is reversed only if the reversal can be related objectively to an event occurring after the impairment loss was recognized.
B128: =+B122+0.1 -> 3.6 | C128: Long term deposits
C130: Deposits are non-derivative financial assets with fixed or determinable payments that are not quoted in an active market. They are included in non-current assets for having maturities greater than 12 months after the reporting date. Initially they are recognized at fair value and subsequently stated at amortized cost.
B132: =B128+0.1 -> 3.7 | C132: Stores and spares
C133: These are valued at lower of cost, which is calculated by using moving average method less any allowance for obsolete and slow moving store items and net realizable value. Stores in transit are stated at invoice value included incidental charges accumulated till the statement of financial position date, if any, incurred thereon. Net realizable value specifies the estimated selling price in the ordinary course of business less the estimated cost of completion and cost necessary to make the sale.
C135: Judgement and Estimates
C136: The company reviews the carry amount of stores, spare parts and loose tools on a regular basis and provision is made for identified obsolete and slow moving items based on their condition at the statement of financial position date depending upon the management's judgement.
B139: =B132+0.1 -> 3.8 | C139: Stock in trade
C140: These have been valued on the basis of lower of cost and net realizable value. The cost is determined, as under:
C141: Food Items & packing materials | H141: at average moving cost
C143: Net realizable value signifies the selling price in the ordinary course of business less estimated costs of completion and selling expenses incidental thereto.
C144: Raw material | G144: - At moving average cost
C145: Finished goods | G145: - At moving average cost
B147: =B139+0.1 -> 3.9 | C147: Cash & cash equivalents
C149: Cash and cash equivalents are carried at cost in the statement of financial position. For the purpose of cash flows, cash and cash equivalents comprises cash in hand and cash at banks in the current and savings accounts.
B151: =B139+0.1 -> 3.9 | C151: Trade and other payables
C153: Liabilities for trade and other payable are carried at cost, which is the fair value of the consideration to be paid in future for the goods and services, whether or not billed to the company.
B155: =B151+0.1 -> 4 | C155: Trade and other receivables
C157: Trade and other receivables are recognized at transaction price less an allowance for impairment.
C158: A provision for impairment of trade receivables is established when there is objective evidence that the Company will not be able to collect all amounts due according to the original terms of the receivables. The amount of the provision is recognized in the statement of profit or loss. Bad debts are written-off in the statement of profit or loss on identification.
C159: The allowance for doubtful debts of the Company is based on the ageing analysis and management’s continuous evaluation of the recoverability of the outstanding receivables. In assessing the ultimate realization of these receivables, management considers, among other factors, the creditworthiness and the past collection history of each customer.
B160: 3.1 | C160: Basic Financial Instruments
C162: Financial Assets
C164: Financial assets are trade and other receivables, long term deposits, due from related parties and cash and bank balances. Financial assets are initially recognized at cost plus transaction costs which is the fair value of the consideration given or received at the time when the Company becomes party to the contractual provisions of the instrument, except for financial assets at fair value through profit or loss, which are initially recognized at fair value and transaction costs are expensed in the statement of profit or loss. The Company derecognizes a financial asset or a portion of financial asset when, and only when, the right to receive the cash flows from the assets have been expired or have been transferred; and the company has transferred substantially all the risks and rewards of ownership or the enterprise loses control of the contractual rights that comprise financial assets or a portion of financial assets.
C166: Financial Liabilities
C168: Financial liabilities are recognized according to the substance of the contractual arrangements entered into. Significant financial liabilities are amounts due to related parties, accrued liabilities and trade creditors. A financial liability is derecognized when the obligation under the liability is discharged, cancelled or expired.
C170: Any gain or loss on the recognition and de-recognition of the financial assets and liabilities is included in the statement of profit or loss for the period in which it arises.
C172: Off setting of financial assets and financial liabilities
C174: A financial asset and financial liability is off set and the net amount is reported in the statement of financial position if the Company has a legally enforceable right to set off the recognized amounts and indents either to settle on a net basis or to realize the asset and settle the liability simultaneously.
B176: =B160+0.01 -> 3.11 | C176: Related party transactions
C178: All transactions with related parties are executed at arm’s length prices, determined in accordance with the pricing method as approved by the Board of Directors, except in the rarely extreme circumstances, where it is in the interest of the company to do so. Parties are said to be related if they are able to influence the operating and financial decisions of the company.
B180: =B176+0.01 -> 3.12 | C180: Provision
C182: A provision is recognized in the statement of financial position of the company when the company has a legal or constructive obligation as a result of a past event; and it is probable that an outflow of economic resources embodying economic benefit will be required to settle the obligation and a reliable estimate can be made of the amount of obligation. However, the provisions are adjusted at each reporting period to reflect the best estimate.
B184: =B180+0.01 -> 3.13 | C184: Contingencies and commitments
C186: A contingent liability is disclosed when the Company has a possible obligation as a result of past events, whose existence will be confirmed only by the occurrence or non-occurrence, of one or more uncertain future events not wholly within the control of the Company; or the Company has a present legal or constructive obligation that arises from past events, but it is not probable that an outflow of resources embodying economic benefits will be required to settle the obligation, or the amount of the obligation cannot be measured with sufficient reliability.
C188: Capital commitments, unless those are actual liabilities, are not incorporated in the books of accounts.
B190: =B184+0.01 -> 3.14 | C190: Revenue recognition
...

Sheet Trial Balance
C1: AIMAL KHAN TRADERS
C2: Trial Balance As At 9 june 2026
B3: Account Name | C3: Debit (Dr) | D3: Credit (Cr)
B4: Fixed Assets - Cost | C4: ='Note 5 ''2025'!C11 -> 11585617
B5: Accumulated Depreciation | D5: ='Note 5 ''2025'!I11 -> 5577526.6
B6: Stores and Spares | C6: =NOTES!L203 -> 85471121
B7: Trade Receivables | C7: =SOFP!D21 -> 77671960
B8: Advances, Deposits & Other Receivables | C8: =NOTES!L213 -> 24183427
B9: Cash and Bank Balances | C9: =NOTES!L219 -> 85418833
B10: Capital Account | D10: =NOTES!L227 -> 1.5258328e+08
B11: Drawings | C11: =NOTES!L231*-1 -> 61005627
B12: Retained Earnings (True Opening Balance)
B13: Long-Term Financing / Loans | D13: =NOTES!L251+NOTES!L270 -> 39280373
B14: Creditors, Accrued Exp. & Other Liab. | D14: =NOTES!L279 -> 44566142
B15: Revenue - Net | D15: =NOTES!L282 -> 8.2445869e+08
B16: Cost of Revenue | C16: =NOTES!L302 -> 6.7175285e+08
B17: Administrative Expenses | C17: =NOTES!L318 -> 32608624
B18: Financial Charges | C18: =NOTES!L337 -> 1327944.7
B19: Taxation for the Year | C19: ='P & L'!J21 -> 15440005
B20: TOTALS | C20: =SUM(C4:C19) -> 1.066466e+09 | D20: =SUM(D4:D19) -> 1.066466e+09 | E20: =D20-C20 -> 0

Sheet Loan
A1: LOAN AMORTISATION SCHEDULE
A2: Loan 1 | M2: Loan 2
A3: 7500000 | M3: 7000000
A4: 0.07 | M4: 0.09
A5: Date | B5: Total Amount | C5: Principal | D5: Interest | E5: Outstanding | F5: Payable | I5: Paid | M5: Date | N5: Total Amount | O5: Principal | P5: Interest | Q5: Outstanding | R5: Payable | U5: Paid
A6: 45457 | B6: 0 | C6: 0 | D6: 0 | E6: 7500000 | M6: 45448 | N6: 0 | O6: 0 | P6: 0 | Q6: 7000000
A7: 45474 | B7: 149385.25 | C7: 125000 | D7: 24385.25 | E7: =+E6-C7 -> 7375000 | M7: 45478 | N7: =+O7+P7 -> 246083.34 | O7: 194444 | P7: 51639.34 | Q7: =+Q6-O7 -> 6805556
A8: 45505 | B8: 168726.09 | C8: 125000 | D8: 43726.09 | E8: =+E7-C8 -> 7250000 | M8: 45509 | N8: =+O8+P8 -> 246322.42 | O8: 194444 | P8: 51878.42 | Q8: =+Q7-O8 -> 6611112
A9: 45536 | B9: =+C9+D9 -> 167984.97 | C9: 125000 | D9: 42984.97 | E9: =+E8-C9 -> 7125000 | M9: 45540 | N9: =+O9+P9 -> 244840.18 | O9: 194444 | P9: 50396.18 | Q9: =+Q8-O9 -> 6416668
A10: 45566 | B10: =+C10+D10 -> 165881.15 | C10: 125000 | D10: 40881.15 | E10: =+E9-C10 -> 7000000 | M10: 45570 | N10: =+O10+P10 -> 241780.08 | O10: 194444 | P10: 47336.08 | Q10: =+Q9-O10 -> 6222224
A11: 45597 | B11: =+C11+D11 -> 166502.73 | C11: 125000 | D11: 41502.73 | E11: =+E10-C11 -> 6875000 | I11: Year 2024 | M11: 45601 | N11: =+O11+P11 -> 241875.71 | O11: 194444 | P11: 47431.71 | Q11: =+Q10-O11 -> 6027780 | U11: Year 2024
A12: 45627 | B12: =+C12+D12 -> 164446.72 | C12: 125000 | D12: 39446.72 | E12: =+E11-C12 -> 6750000 | I12: Interest | J12: Principal | M12: 45631 | N12: =+O12+P12 -> 238911.23 | O12: 194444 | P12: 44467.23 | Q12: =+Q11-O12 -> 5833336 | U12: Interest | V12: Principal
A13: 45658 | B13: =+C13+D13 -> 165020.49 | C13: 125000 | D13: 40020.49 | E13: =+E12-C13 -> 6625000 | I13: =SUM(D7:D13) -> 272947.4 | J13: =SUM(C7:C13) -> 875000 | M13: 45662 | N13: =+O13+P13 -> 238926.95 | O13: 194444 | P13: 44482.95 | Q13: =+Q12-O13 -> 5638892 | U13: =SUM(P7:P13) -> 337631.91 | V13: =SUM(O7:O13) -> 1361108
A14: 45689 | B14: =+C14+D14 -> 164388.99 | C14: 125000 | D14: 39388.99 | E14: =+E13-C14 -> 6500000 | M14: 45693 | N14: =+O14+P14 -> 237546.76 | O14: 194444 | P14: 43102.76 | Q14: =+Q13-O14 -> 5444448
A15: 45717 | B15: =+C15+D15 -> 159904.11 | C15: 125000 | D15: 34904.11 | E15: =+E14-C15 -> 6375000 | M15: 45721 | N15: =+O15+P15 -> 232033.07 | O15: 194444 | P15: 37589.07 | Q15: =+Q14-O15 -> 5250004
A16: 45748 | B16: =+C16+D16 -> 162900.68 | C16: 125000 | D16: 37900.68 | E16: =+E15-C16 -> 6250000 | M16: 45752 | N16: =+O16+P16 -> 234574.17 | O16: 194444 | P16: 40130.17 | Q16: =+Q15-O16 -> 5055560
A17: 45778 | B17: =+C17+D17 -> 160958.8 | C17: 125000 | D17: 35958.8 | E17: =+E16-C17 -> 6125000 | M17: 45782 | N17: =+O17+P17 -> 231841.29 | O17: 194444 | P17: 37397.29 | Q17: =+Q16-O17 -> 4861116
A18: 45809 | B18: =+C18+D18 -> 161414.38 | C18: 125000 | D18: 36414.38 | E18: =+E17-C18 -> 6000000 | M18: 45813 | N18: =+O18+P18 -> 231601.57 | O18: 194444 | P18: 37157.57 | Q18: =+Q17-O18 -> 4666672
A19: 45839 | B19: =+C19+D19 -> 159520.55 | C19: 125000 | D19: 34520.55 | E19: =+E18-C19 -> 5875000 | M19: 45843 | N19: =+O19+P19 -> 228964.59 | O19: 194444 | P19: 34520.59 | Q19: =+Q18-O19 -> 4472228
A20: 45870 | B20: =+C20+D20 -> 159928.08 | C20: 125000 | D20: 34928.08 | E20: =+E19-C20 -> 5750000 | M20: 45874 | N20: =+O20+P20 -> 228628.98 | O20: 194444 | P20: 34184.98 | Q20: =+Q19-O20 -> 4277784
A21: 45901 | B21: =+C21+D21 -> 159184.93 | C21: 125000 | D21: 34184.93 | E21: =+E20-C21 -> 5625000 | M21: 45905 | N21: =+O21+P21 -> 227142.68 | O21: 194444 | P21: 32698.68 | Q21: =+Q20-O21 -> 4083340
A22: 45931 | B22: =+C22+D22 -> 157363.01 | C22: 125000 | D22: 32363.01 | E22: =+E21-C22 -> 5500000 | M22: 45935 | N22: =+O22+P22 -> 224649.53 | O22: 194444 | P22: 30205.53 | Q22: =+Q21-O22 -> 3888896
A23: 45962 | B23: =+C23+D23 -> 157698.63 | C23: 125000 | D23: 32698.63 | E23: =+E22-C23 -> 5375000 | F23: Year 2024 | I23: Year 2025 | M23: 45966 | N23: =+O23+P23 -> 224170.08 | O23: 194444 | P23: 29726.08 | Q23: =+Q22-O23 -> 3694452 | R23: Year 2024 | U23: Year 2025
A24: 45992 | B24: =+C24+D24 -> 155469.18 | C24: 125000 | D24: 30469.18 | E24: =+E23-C24 -> 5250000 | F24: Principal | G24: Interest | I24: Interest | J24: Principal | M24: 45996 | N24: =+O24+P24 -> 221772.82 | O24: 194444 | P24: 27328.82 | Q24: =+Q23-O24 -> 3500008 | R24: Principal | S24: Interest | U24: Interest | V24: Principal
A25: 46023 | B25: =+C25+D25 -> 156212.33 | C25: 125000 | D25: 31212.33 | E25: =+E24-C25 -> 5125000 | F25: =+E13-E25 -> 1500000 | G25: =SUM(D14:D25) -> 414943.67 | H25: CL | I25: =SUM(D14:D25) -> 414943.67 | J25: =SUM(C14:C25) -> 1500000 | M25: 46027 | N25: =+O25+P25 -> 221197.49 | O25: 194444 | P25: 26753.49 | Q25: =+Q24-O25 -> 3305564 | R25: =+Q13-Q25 -> 2333328 | S25: =SUM(P14:P25) -> 410795.03 | T25: CL | U25: =SUM(P14:P25) -> 410795.03 | V25: =SUM(O14:O25) -> 2333328
A26: 46054 | B26: =+C26+D26 -> 155469.18 | C26: 125000 | D26: 30469.18 | E26: =+E25-C26 -> 5000000 | F26: =+E25 -> 5125000 | G26: =SUM(D26:D66) -> 627389.65 | H26: NCL | M26: 46058 | N26: =+O26+P26 -> 219711.19 | O26: 194444 | P26: 25267.19 | Q26: =+Q25-O26 -> 3111120 | R26: =+Q25 -> 3305564 | S26: =SUM(P26:P42) -> 222419.33 | T26: NCL
A27: 46082 | B27: =+C27+D27 -> 151849.32 | C27: 125000 | D27: 26849.32 | E27: =+E26-C27 -> 4875000 | M27: 46086 | N27: =+O27+P27 -> 215923.51 | O27: 194444 | P27: 21479.51 | Q27: =+Q26-O27 -> 2916676
A28: 46113 | B28: =+C28+D28 -> 153982.88 | C28: 125000 | D28: 28982.88 | E28: =+E27-C28 -> 4750000 | M28: 46117 | N28: =+O28+P28 -> 216738.59 | O28: 194444 | P28: 22294.59 | Q28: =+Q27-O28 -> 2722232
A29: 46143 | B29: =+C29+D29 -> 152328.77 | C29: 125000 | D29: 27328.77 | E29: =+E28-C29 -> 4625000 | M29: 46147 | N29: =+O29+P29 -> 214581.06 | O29: 194444 | P29: 20137.06 | Q29: =+Q28-O29 -> 2527788
A30: 46174 | B30: =+C30+D30 -> 152498.58 | C30: 125000 | D30: 27498.58 | E30: =+E29-C30 -> 4500000 | M30: 46178 | N30: =+O30+P30 -> 213766 | O30: 194444 | P30: 19322 | Q30: =+Q29-O30 -> 2333344
A31: 46204 | B31: =+C31+D31 -> 150890.41 | C31: 125000 | D31: 25890.41 | E31: =+E30-C31 -> 4375000 | M31: 46208 | N31: =+O31+P31 -> 211704.35 | O31: 194444 | P31: 17260.35 | Q31: =+Q30-O31 -> 2138900
A32: 46235 | B32: =+C32+D32 -> 151010.27 | C32: 125000 | D32: 26010.27 | E32: =+E31-C32 -> 4250000 | M32: 46239 | N32: =+O32+P32 -> 210793.4 | O32: 194444 | P32: 16349.4 | Q32: =+Q31-O32 -> 1944456
A33: 46266 | B33: =+C33+D33 -> 150267.12 | C33: 125000 | D33: 25267.12 | E33: =+E32-C33 -> 4125000 | M33: 46270 | N33: =+O33+P33 -> 209307.1 | O33: 194444 | P33: 14863.1 | Q33: =+Q32-O33 -> 1750012
A34: 46296 | B34: =+C34+D34 -> 148732.88 | C34: 125000 | D34: 23732.88 | E34: =+E33-C34 -> 4000000 | M34: 46300 | N34: =+O34+P34 -> 207389.29 | O34: 194444 | P34: 12945.29 | Q34: =+Q33-O34 -> 1555568
A35: 46327 | B35: =+C35+D35 -> 148780.82 | C35: 125000 | D35: 23780.82 | E35: =+E34-C35 -> 3875000 | F35: Year 2025 | M35: 46331 | N35: =+O35+P35 -> 206334.51 | O35: 194444 | P35: 11890.51 | Q35: =+Q34-O35 -> 1361124 | R35: Year 2025
A36: 46357 | B36: =+C36+D36 -> 147294.52 | C36: 125000 | D36: 22294.52 | E36: =+E35-C36 -> 3750000 | F36: Principal | G36: Interest | M36: 46361 | N36: =+O36+P36 -> 204512.59 | O36: 194444 | P36: 10068.59 | Q36: =+Q35-O36 -> 1166680 | R36: Principal | S36: Interest
A37: 46388 | B37: =+C37+D37 -> 147294.52 | C37: 125000 | D37: 22294.52 | E37: =+E36-C37 -> 3625000 | F37: =+E25-E37 -> 1500000 | G37: =SUM(D26:D37) -> 310399.27 | H37: CL | M37: 46392 | N37: =+O37+P37 -> 203361.91 | O37: 194444 | P37: 8917.91 | Q37: =+Q36-O37 -> 972236 | R37: =+Q25-Q37 -> 2333328 | S37: =SUM(P26:P37) -> 200795.5 | T37: CL
A38: 46419 | B38: =+C38+D38 -> 146651.37 | C38: 125000 | D38: 21651.37 | E38: =+E37-C38 -> 3500000 | F38: =+E37 -> 3625000 | G38: =SUM(D38:D66) -> 316990.38 | H38: NCL | M38: 46423 | N38: =+O38+P38 -> 201875.61 | O38: 194444 | P38: 7431.61 | Q38: =+Q37-O38 -> 777792 | R38: =+Q37 -> 972236 | S38: =SUM(P38:P42) -> 21623.83 | T38: NCL
A39: 46447 | B39: =+C39+D39 -> 143794.52 | C39: 125000 | D39: 18794.52 | E39: =+E38-C39 -> 3375000 | M39: 46451 | N39: =+O39+P39 -> 199813.96 | O39: 194444 | P39: 5369.96 | Q39: =+Q38-O39 -> 583348
A40: 46478 | B40: =+C40+D40 -> 145065.07 | C40: 125000 | D40: 20065.07 | E40: =+E39-C40 -> 3250000 | M40: 46482 | N40: =+O40+P40 -> 198903.02 | O40: 194444 | P40: 4459.02 | Q40: =+Q39-O40 -> 388904
A41: 46508 | B41: =+C41+D41 -> 143698.63 | C41: 125000 | D41: 18698.63 | E41: =+E40-C41 -> 3125000 | M41: 46512 | N41: =+O41+P41 -> 197320.82 | O41: 194444 | P41: 2876.82 | Q41: =+Q40-O41 -> 194460
A42: 46539 | B42: =+C42+D42 -> 143578.77 | C42: 125000 | D42: 18578.77 | E42: =+E41-C42 -> 3000000 | M42: 46543 | N42: =+O42+P42 -> 195946.42 | O42: 194460 | P42: 1486.42 | Q42: =+Q41-O42 -> 0
A43: 46569 | B43: =+C43+D43 -> 142260.27 | C43: 125000 | D43: 17260.27 | E43: =+E42-C43 -> 2875000 | N43: =SUM(N6:N42) -> 7970846.3 | O43: =SUM(O6:O42) -> 7000000 | P43: =SUM(P6:P42) -> 970846.27
A44: 46600 | B44: =+C44+D44 -> 142092.47 | C44: 125000 | D44: 17092.47 | E44: =+E43-C44 -> 2750000
A45: 46631 | B45: =+C45+D45 -> 141349.32 | C45: 125000 | D45: 16349.32 | E45: =+E44-C45 -> 2625000
A46: 46661 | B46: =+C46+D46 -> 140102.74 | C46: 125000 | D46: 15102.74 | E46: =+E45-C46 -> 2500000
A47: 46692 | B47: =+C47+D47 -> 139863.01 | C47: 125000 | D47: 14863.01 | E47: =+E46-C47 -> 2375000
A48: 46722 | B48: =+C48+D48 -> 138864.38 | C48: 125000 | D48: 13864.38 | E48: =+E47-C48 -> 2250000
A49: 46753 | B49: =+C49+D49 -> 138376.71 | C49: 125000 | D49: 13376.71 | E49: =+E48-C49 -> 2125000
A50: 46784 | B50: =+C50+D50 -> 137599.04 | C50: 125000 | D50: 12599.04 | E50: =+E49-C50 -> 2000000
A51: 46813 | B51: =+C51+D51 -> 136092.9 | C51: 125000 | D51: 11092.9 | E51: =+E50-C51 -> 1875000
A52: 46844 | B52: =+C52+D52 -> 136116.8 | C52: 125000 | D52: 11116.8 | E52: =+E51-C52 -> 1750000
A53: 46874 | B53: =+C53+D53 -> 135040.98 | C53: 125000 | D53: 10040.98 | E53: =+E52-C53 -> 1625000
A54: 46905 | B54: =+C54+D54 -> 134634.56 | C54: 125000 | D54: 9634.56 | E54: =+E53-C54 -> 1500000
A55: 46935 | B55: =+C55+D55 -> 133606.56 | C55: 125000 | D55: 8606.56 | E55: =+E54-C55 -> 1375000
... A66: 47269 | B66: =+C66+D66 -> 125719.18 | C66: 125000 | D66: 719.18 | E66: =+E65-C66 -> 0
B67: =SUM(B6:B66) -> 8815280.7 | C67: =SUM(C6:C66) -> 7500000 | D67: =SUM(D6:D66) -> 1315280.7

Sheet Note 5
A1: 5 | B1: FIXED ASSETS
B3: PARTICULARS | C3: COST | F3: Rate% | G3: DEPRECIATION | J3: W.D.V As at 31/12/2024
C4: As at 1/1/2024 | D4: Additions / Deletions | E4: As at 31/12/2024 | G4: As at 1/1/2024 | H4: For the Year | I4: As at 31/12/2024
B6: Office Decoration | C6: 1503162 | D6: 0 | E6: =+C6+D6 -> 1503162 | F6: 0.1 | G6: 615560 | H6: =(E6-G6)*0.1 -> 88760.2 | I6: =+G6+H6 -> 704320.2 | J6: =+E6-I6 -> 798841.8
B7: Motor Vehicles | C7: 9469948 | E7: =+C7+D7 -> 9469948 | F7: 0.1 | G7: 3329263 | H7: =(E7-G7)*0.1 -> 614068.5 | I7: =+G7+H7 -> 3943331.5 | J7: =+E7-I7 -> 5526616.5
B8: Furniture & Fixtures | C8: 354122 | D8: 0 | E8: =+C8+D8 -> 354122 | F8: 0.1 | G8: 117578 | H8: =(E8-G8)*0.1 -> 23654.4 | I8: =+G8+H8 -> 141232.4 | J8: =+E8-I8 -> 212889.6
B9: Computer & Electric Equipments | C9: 192550 | E9: =+C9+D9 -> 192550 | F9: 0.1 | G9: 78860 | H9: =(E9-G9)*0.1 -> 11369 | I9: =+G9+H9 -> 90229 | J9: =+E9-I9 -> 102321
B10: Other Assets | C10: 65835 | D10: 0 | E10: =+C10+D10 -> 65835 | F10: 0.1 | G10: 26960 | H10: =(E10-G10)*0.1 -> 3887.5 | I10: =+G10+H10 -> 30847.5 | J10: =+E10-I10 -> 34987.5
B11: 2024 | C11: =SUM(C6:C10) -> 11585617 | D11: =SUM(D6:D10) -> 0 | E11: =SUM(E6:E10) -> 11585617 | G11: =SUM(G6:G10) -> 4168221 | H11: =SUM(H6:H10) -> 741739.6 | I11: =SUM(I6:I10) -> 4909960.6 | J11: =SUM(J6:J10) -> 6675656.4
J12: \
B13: 2023 | C13: =+C11 -> 11585617 | E13: =+C13 -> 11585617 | G13: 3344066 | H13: 824155 | I13: =+G13+H13 -> 4168221 | J13: =+C13-I13 -> 7417396
A15: 5.1 | B15: Deprecation for the year has been allocated as under:
G16: 2025 | H16: 2024 | I16: 2023
G17: Rupees | H17: Rupees | I17: Rupees
C18: Cost of Sales | H18: =H11*0.8 -> 593391.68 | I18: =H13*0.8 -> 659324
C19: Operating Expenses | H19: =H11*0.2 -> 148347.92 | I19: =H13*0.2 -> 164831
G20: =SUM(G18:G19) -> 0 | H20: =SUM(H18:H19) -> 741739.6 | I20: =SUM(I18:I19) -> 824155

Sheet DEP 2017
A4: 3. | B4: FIXED ASSETS
B6: P A R T I C U L A R S | D6: C O S T | G6: Rate (%) | H6: D E P R E C I A T I O N | L6: W.D.V
D7: As at 01-04-2022 | E7: Additions | F7: As at 31-03-2023 | H7: =D7 -> As at 01-04-2022 | I7: For the year | J7: =F7 -> As at 31-03-2023 | L7: =J7 -> As at 31-03-2023
B11: Residential House (Street No. 4 Gujrat) | D11: 45000000 | F11: =+D11+E11 -> 45000000 | H11: 0 | J11: =SUM(H11:I11) -> 0 | L11: =+F11-J11 -> 45000000
B12: Residential House (DHA, Rawalpindi) | D12: 47000000 | F12: =+D12+E12 -> 47000000 | H12: 0 | J12: =SUM(H12:I12) -> 0 | L12: =+F12-J12 -> 47000000
B13: Residential House (Kathala Chenab) | D13: 15000000 | F13: =+D13+E13 -> 15000000 | H13: 0 | J13: =SUM(H13:I13) -> 0 | L13: =+F13-J13 -> 15000000
B14: Poultry Farm (Control Shed) | D14: 22000000 | F14: =+D14+E14 -> 22000000 | L14: =+F14-J14 -> 22000000
B15: Office Building (3264-sq.ft.) | D15: 9000000 | F15: =+D15+E15 -> 9000000 | L15: =+F15-J15 -> 9000000
B18: RUPEES: 2023 | D18: =SUM(D11:D17) -> 138000000 | E18: =SUM(E11:E15) -> 0 | F18: =SUM(F11:F15) -> 138000000 | H18: =SUM(H11:H15) -> 0 | I18: =SUM(I11:I15) -> 0 | J18: =SUM(J11:J15) -> 0 | L18: =SUM(L11:L15) -> 138000000
B20: RUPEES : 2022 | D20: =D18 -> 138000000 | E20: 0 | F20: =F18 -> 138000000 | L20: =L18 -> 138000000

Sheet Sheet3
F4: 2019
B5: Name of related parties | D5: Nature of transactions | F5: Rupees
B7: HM Holding Company | D7: Working capital assistance provided | F7: ='Trial Combine 19'!J242 -> 25401670

Sheet FIXED ASSETS
E4: COST | P4: DEPRECIATION | Z4: Written down | AB4: DEPRECIATION | AD4: Written down
B5: Particulars | E5: As at | G5: Additions | I5: Deletion / | L5: As at | N5: Rate | P5: As at | R5: Deletion / Transfer | T5: Adjustment | V5: For the | X5: As at | Z5: value as on | AB5: For the | AD5: value as on
E6: July 01, 2018 | I6: Transfer | L6: June 30, 2019 | N6: % | P6: July 01, 2018 | V6: year | X6: June 30, 2019 | Z6: June 30, 2019 | AB6: year | AD6: June 30, 2020 | AF6: =K24-SOFP!#REF! -> #REF!
B9: Owned
B11: Furniture and fixtures | E11: 0 | G11: 0 | I11: 0 | K11: 700000 | L11: =E11+K11 -> 700000 | N11: 30 | P11: 0 | R11: 0 | T11: 0 | V11: 35000 | X11: 35000 | Z11: =L11-X11 -> 665000 | AB11: =Z11*N11% -> 199500 | AD11: =Z11-AB11 -> 465500 | AF11: 276203 | AG11: =X11-AF11 -> -241203 | AH11: =E11-P11 -> 0 | AI11: =AH11*0.1 -> 0
B12: Office equipment | E12: 0 | G12: 0 | I12: 0 | K12: 112428 | L12: =E12+K12 -> 112428 | N12: 15 | P12: 0 | R12: 0 | T12: 0 | V12: 4479 | X12: 4479 | Z12: =L12-X12 -> 107949 | AB12: =Z12*N12% -> 16192.35 | AD12: =Z12-AB12 -> 91756.65 | AF12: 246294 | AG12: =X12-AF12 -> -241815 | AH12: =E12-P12 -> 0 | AI12: =AH12*0.1 -> 0 | AJ12: =G12*0.1 -> 0
B13: Computers | E13: 0 | K13: =94175+84293+180890 -> 359358 | L13: =E13+K13 -> 359358 | N13: 15 | P13: 0 | V13: 61441 | X13: 61441 | Z13: =L13-X13 -> 297917 | AB13: =Z13*N13% -> 44687.55 | AD13: =Z13-AB13 -> 253229.45
B14: Machinery | E14: 0 | K14: =282722+487639+130000+1670980+160000+45000+114618 -> 2890959 | L14: =E14+K14 -> 2890959 | N14: 15 | P14: 0 | V14: 163328 | X14: 163328 | Z14: =L14-X14 -> 2727631 | AB14: =Z14*N14% -> 409144.65 | AD14: =Z14-AB14 -> 2318486.4
B15: Games equipment | E15: 0 | G15: 0 | I15: 0 | K15: =198500+533500 -> 732000 | L15: =E15+K15 -> 732000 | N15: 15 | P15: 0 | R15: 0 | T15: 0 | V15: 27363 | X15: 27363 | Z15: =L15-X15 -> 704637 | AB15: =Z15*N15% -> 105695.55 | AD15: =Z15-AB15 -> 598941.45 | AF15: 444795 | AG15: =X15-AF15 -> -417432 | AH15: =E15-P15 -> 0 | AI15: =AH15*0.25 -> 0
B16: Generator | E16: 0 | G16: 0 | I16: 0 | K16: 1068000 | L16: =E16+K16 -> 1068000 | N16: 15 | P16: 0 | R16: 0 | T16: 0 | V16: 37550 | X16: 37550 | Z16: =L16-X16 -> 1030450 | AB16: =Z16*N16% -> 154567.5 | AD16: =Z16-AB16 -> 875882.5 | AF16: 580390 | AG16: =X16-AF16 -> -542840 | AH16: =E16-P16 -> 0 | AI16: =AH16*0.1 -> 0
B17: Leasehold improvement | E17: 0 | G17: 0 | I17: 0 | K17: 8780816 | L17: =E17+K17 -> 8780816 | N17: 15 | P17: 0 | R17: 0 | T17: 0 | V17: 532276 | X17: 532276 | Z17: =L17-X17 -> 8248540 | AB17: =Z17*N17% -> 1237281 | AD17: =Z17-AB17 -> 7011259 | AF17: 1402849 | AG17: =X17-AF17 -> -870573 | AH17: =E17-P17 -> 0 | AI17: =AH17*0.2 -> 0 | AJ17: =G17*0.2 -> 0
B19: Leased
B21: Motor vehicle | E21: 0 | K21: 0 | L21: 0 | N21: 20 | P21: =X41 -> 0 | R21: 0 | X21: =ROUND(P21+R21+V21+T21,0) -> 0 | Z21: =ROUND(L21-X21,0) -> 0
L22: 0
B24: 2019 | C24: Rupees | E24: =SUM(E11:F21) -> 0 | G24: =SUM(G11:H21) -> 0 | I24: =SUM(I11:I21) -> 0 | K24: =SUM(K11:K23) -> 14643561 | L24: =SUM(L11:L21) -> 14643561 | P24: =SUM(P11:P21) -> 0 | R24: =SUM(R11:R21) -> 0 | T24: =SUM(T11:T21) -> 0 | V24: =SUM(V11:V21) -> 861437 | X24: =SUM(X11:X21) -> 861437 | Z24: =SUM(Z11:Z21) -> 13782124 | AB24: =SUM(AB11:AB21) -> 2167068.6 | AD24: =SUM(AD11:AD21) -> 11615055 | AF24: =SUM(AF11:AF23) -> 2950531 | AG24: =SUM(AG11:AG17) -> -2313863 | AI24: =SUM(AI11:AI23) -> 0 | AJ24: =SUM(AJ11:AJ23) -> 0
AH25: =435806-435949 -> -143 | AI25: =435877-435806 -> 71 | AJ25: =AI24+AJ24 -> 0 | AL25: 320298
E26: COST | P26: DEPRECIATION | Z26: Written down | AF26: 307413 | AL26: =V24-AL25 -> 541139
B27: Particulars | E27: As at | G27: Additions | I27: Deletion / | L27: As at | N27: Rate | P27: As at | R27: Deletion / Transfer | T27: Adjustment | V27: For the | X27: As at | Z27: value as on | AF27: 12885
E28: July 01, 2017 | I28: Transfer | L28: June 30, 2018 | N28: % | P28: July 01, 2017 | V28: year | X28: June 30, 2018 | Z28: June 30, 2018 | AF28: =SUM(AF26:AF27) -> 320298 | AG28: =V24-AF28 -> 541139
AH29: =13628+8547+3152 -> 25327 | AJ29: Dep | AK29: =AG28 -> 541139
B30: Owned | AJ30: Acc.dep-equip | AK30: 638
AJ31: Acc dep-gen | AK31: 479271
B32: Furniture and fixtures | E32: 321951 | G32: 0 | I32: 0 | L32: 321951 | N32: 10 | P32: 259385 | R32: 0 | T32: 0 | V32: 6257 | X32: =P32+V32 -> 265642 | Z32: =L32-X32 -> 56309 | AJ32: Acc dep-mot | AK32: 499532
B33: Office equipment | E33: 720786 | G33: 0 | I33: 0 | L33: 720786 | N33: 10 | P33: 503541 | R33: 0 | T33: 0 | V33: 21725 | X33: =P33+V33 -> 525266 | Z33: =L33-X33 -> 195520 | AH33: =Z33+Z34+Z35 -> 265743
B34: Computer equipment | E34: 472830 | G34: 0 | I34: 0 | L34: 472830 | N34: 25 | P34: 444157 | R34: 0 | T34: 0 | V34: 7168 | X34: =P34+V34 -> 451325 | Z34: =L34-X34 -> 21505 | AJ34: Acc dep-office | AL34: =AG12 -> -241815
B35: Generator | E35: 155250 | G35: 0 | I35: 0 | L35: 155250 | N35: 10 | P35: 101119 | R35: 0 | T35: 0 | V35: 5413 | X35: =P35+V35 -> 106532 | Z35: =L35-X35 -> 48718 | AJ35: Acc dep-vehicles | AL35: =AG17 -> -870573
B36: Motor vehicle | E36: 3392675 | G36: 0 | I36: 0 | L36: 3392675 | N36: 20 | P36: 2173692 | R36: 0 | T36: 0 | V36: 243797 | X36: =P36+V36 -> 2417489 | Z36: =L36-X36 -> 975186
B37: Motor cycle | E37: 73000 | G37: 0 | I37: 0 | L37: 73000 | N37: 20 | P37: 70109 | R37: 0 | T37: 0 | V37: 578 | X37: =P37+V37 -> 70687 | Z37: =L37-X37 -> 2313 | AH37: 954386 | AK37: =SUM(AK29:AK36) -> 1520580 | AL37: =SUM(AL34:AL36) -> -1112388
B43: 2018 | C43: Rupees | E43: =SUM(E32:F41) -> 5136492 | G43: =SUM(G32:G41) -> 0 | I43: =SUM(I32:I41) -> 0 | L43: =SUM(L32:L41) -> 5136492 | P43: =SUM(P32:P41) -> 3552003 | Q43: =SUM(Q32:Q41) -> 0 | R43: =SUM(R32:R41) -> 0 | T43: =SUM(T32:T41) -> 0 | V43: =SUM(V32:V41) -> 284938 | W43: =SUM(W32:W41) -> 0 | X43: =SUM(X32:X41) -> 3836941 | Z43: =SUM(Z32:Z41) -> 1299551 | AH43: =5278*6 -> 31668
AH46: =5628*6 -> 33768

Sheet Fixed Assets A 
A2: 5 | B2: PROPERTY, PLANT AND EQUIPMENT | D2: 2020 | F2: 2019
D3: Rupees | F3: Rupees
B5: Property , plant and equipments (Note 5.1) | D5: =S50 -> 14831979 | F5: =S20 -> 13782124
A8: =A2+0.1 -> 5.1 | B8: Reconciliation of carrying amounts at the beginning and end of the year is as follows:
D10: Owned | S10: Total Operating assets
D11: Furniture and fixtures | F11: Office equipment | H11: Computers | J11: Machinery | L11: Games equipment | N11: Generator | P11: Leasehold improvement
D12: ------------------------------------------------------------------- Rupees ----------------------------------------------------------------------
B14: Year ended 30 June 2019
B15: Opening net book value
B16: Additions | D16: 700000 | F16: 112428 | H16: =94175+84293+180890 -> 359358 | J16: =282722+487639+130000+1670980+160000+45000+114618 -> 2890959 | L16: =198500+533500 -> 732000 | N16: 1068000 | P16: 8780816 | S16: =SUM(D16:Q16) -> 14643561
B17: Disposal/Transfer to IAS-40 | D17: 0 | F17: 0 | H17: 0 | J17: 0 | L17: 0 | N17: 0 | P17: 0 | S17: 0
B18: Depreciation | D18: =-D16*D54*4/12 -> -35000 | F18: -4479 | H18: -61441 | J18: -163328 | L18: -27363 | N18: -37550 | P18: -532276 | S18: =SUM(D18:Q18) -> -861437
B20: Closing net book value | D20: =SUM(D16:D19) -> 665000 | F20: =SUM(F16:F19) -> 107949 | H20: =SUM(H16:H19) -> 297917 | J20: =SUM(J16:J19) -> 2727631 | L20: =SUM(L16:L19) -> 704637 | N20: =SUM(N16:N19) -> 1030450 | P20: =SUM(P16:P19) -> 8248540 | S20: =SUM(S16:S19) -> 13782124 | T20: =S20-12730250 -> 1051874
B22: At 30 June 2019
B24: Cost | D24: =D16 -> 700000 | F24: =F16 -> 112428 | H24: =H16 -> 359358 | J24: =J16 -> 2890959 | K24: =K16 -> 0 | L24: =L16 -> 732000 | M24: =M16 -> 0 | N24: =N16 -> 1068000 | O24: =O16 -> 0 | P24: =P16 -> 8780816 | Q24: =Q16 -> 0 | ... S24: =S16 -> 14643561
B25: Accumulated depreciation | D25: =D18 -> -35000 | F25: =F18 -> -4479 | G25: =G18 -> 0 | H25: =H18 -> -61441 | J25: =J18 -> -163328 | K25: =K18 -> 0 | L25: =L18 -> -27363 | M25: =M18 -> 0 | N25: =N18 -> -37550 | O25: =O18 -> 0 | P25: =P18 -> -532276 | Q25: =Q18 -> 0 | ... S25: =S18 -> -861437
B26: Net book value | D26: =D24+D25 -> 665000 | F26: =F24+F25 -> 107949 | H26: =H24+H25 -> 297917 | J26: =J24+J25 -> 2727631 | L26: =L24+L25 -> 704637 | N26: =N24+N25 -> 1030450 | P26: =P24+P25 -> 8248540 | S26: =S24+S25 -> 13782124
B28: Year ended 30 June 2020
B29: Opening net book value | D29: =D26 -> 665000 | F29: =F26 -> 107949 | H29: =H26 -> 297917 | J29: =J26 -> 2727631 | L29: =L26 -> 704637 | N29: =N26 -> 1030450 | P29: =P26 -> 8248540 | S29: =SUM(D29:Q29) -> 13782124
B30: Additions | D30: 38000 | F30: 16200 | H30: 0 | J30: 70000 | L30: 1190000 | N30: 0 | P30: 0 | S30: =SUM(D30:Q30) -> 1314200
B32: Disposal
B33: Cost | D33: 0 | F33: 0 | H33: 0 | J33: 0 | L33: 0 | N33: 0 | P33: 0 | S33: =SUM(D33:Q33) -> 0
B34: Accumulated depreciation | D34: 0 | F34: 0 | H34: 0 | J34: 0 | L34: 0 | N34: 0 | P34: 0 | S34: =SUM(D34:Q34) -> 0
B35: Net book value-(disposal) | D35: =D34+D33 -> 0 | F35: =F34+F33 -> 0 | H35: =H34+H33 -> 0 | J35: =J34+J33 -> 0 | L35: =L34+L33 -> 0 | N35: =N34+N33 -> 0 | P35: =P34+P33 -> 0 | S35: =S34+S33 -> 0
B37: Transfer to IAS-40
B38: Cost | D38: 0 | F38: 0 | H38: 0 | J38: 0 | L38: 0 | N38: 0 | P38: 0 | S38: =SUM(D38:Q38) -> 0
B39: Accumulated depreciation | D39: 0 | F39: 0 | H39: 0 | J39: 0 | L39: 0 | N39: 0 | P39: 0 | S39: =SUM(D39:Q39) -> 0
B40: Net book value-(transfer) | D40: =D39+D38 -> 0 | F40: =F39+F38 -> 0 | H40: =H39+H38 -> 0 | J40: =J39+J38 -> 0 | L40: =L39+L38 -> 0 | N40: =N39+N38 -> 0 | P40: =P39+P38 -> 0 | S40: =S39+S38 -> 0
B42: Depreciation | D42: =-((D29+D30)*D54%) -> -1054.5 | F42: =-((F29+F30)*F54%) -> -186.2235 | H42: =-((H29)*H54%)-78107 -> -79000.751 | J42: =-((J29)*J54%)-164797 -> -168888.45 | L42: =-((L29+L30+L40)*L54%) -> -2841.9555 | N42: 0 | P42: =-((P29+P30)*P54%) -> -12372.81 | S42: =SUM(D42:Q42) -> -264344.69
B44: Closing net book value | D44: =D29+D30-D35+D42 -> 701945.5 | F44: =F29+F30-F35+F42 -> 123962.78 | H44: =H29+H30-H35+H42 -> 218916.25 | J44: =J29+J30-J35+J42 -> 2628742.6 | L44: =L29+L40+L42 -> 701795.04 | N44: =N29+N30-N35+N42 -> 1030450 | P44: =P29+P30-P35+P42 -> 8236167.2 | S44: =S29+S30-S35+S42 -> 14831979
B46: At 30 June 2020
B48: Cost | D48: =D24+D30-D33 -> 738000 | F48: =F24+F30-F33 -> 128628 | H48: =H24+H30-H33 -> 359358 | J48: =J24+J30-J33 -> 2960959 | L48: =L24+L30-L33+L38 -> 1922000 | N48: =N24+N30-N33 -> 1068000 | P48: =P24+P30-P33 -> 8780816 | S48: =SUM(D48:Q48) -> 15957761
B49: Accumulated depreciation | D49: =D25+D42 -> -36054.5 | F49: =F25+F42 -> -4665.2235 | H49: =H25+H42 -> -140441.75 | J49: =J25+J42 -> -332216.45 | L49: =L25+L42+L39 -> -30204.956 | N49: =N25+N42-N34 -> -37550 | P49: =P25+P42 -> -544648.81 | S49: =SUM(D49:Q49) -> -1125781.7
B50: Net book value | D50: =D48+D49 -> 701945.5 | F50: =F48+F49 -> 123962.78 | H50: =H48+H49 -> 218916.25 | J50: =J48+J49 -> 2628742.6 | L50: =L48+L49 -> 1891795 | N50: =N48+N49 -> 1030450 | P50: =P48+P49 -> 8236167.2 | S50: =S48+S49 -> 14831979
B54: Annual rate of depreciation (%) | D54: 0.15 | F54: 0.15 | H54: 0.3 | J54: 0.15 | L54: 0.15 | N54: 0.15 | P54: 0.15

Sheet C.tax computation
A1: FOOD CARAVAN (PVT) LTD
A2: TAXABLE INCOME FOR THE YEAR ENDED JUNE 30, 2020
I4: RUPEES | K4: RUPEES
A5: TAXABLE LOSS
B7: Net loss as per accounts | I7: =+'P & L'!P19 -> 0 | K7: =+'P & L'!#REF! -> #REF!
B9: Add: Accounting depreciation | I9: =-'FA-04'!L163 -> 0 | K9: ='FIXED ASSETS'!V24 -> 861437
C10: Amortization | I10: =-NOTES!#REF! -> #REF! | K10: 0
C11: Addition in unrecognized P. Fund | I11: 0 | K11: 0 | N11: =M11/2 -> 0
I12: =SUM(I9:I11) -> #REF! | K12: =SUM(K9:K11) -> 861437
I13: =I7+I12 -> #REF! | K13: =K7+K12 -> #REF!
B15: Less: | C15: Tax depreciation | I15: ='Tax dep'!L25 -> 0 | K15: ='Tax dep'!N25 -> 3280859.9
I16: 0 | K16: 0
I17: =SUM(I15:I16) -> 0 | K17: =SUM(K15:K16) -> 3280859.9
B19: Taxable loss | I19: =I13-I17 -> #REF! | K19: =K13-K17 -> #REF!
A21: COMPUTATION OF TAX ON NORMAL LAW INCOME
B23: (1 | C23: Tax under normal law @ 29 % | I23: 0 | K23: 0
C25: Less adjustment of minimum tax | M25: Less adjustment of minimum tax for the tax years 2011, 2012 & 2013
M26: Rs 416,061 + ( Rs 251,961 - Rs 215,427 )
M27: From Last Audited Accounts | N27: Normal Tax for the tax year 2013 | P27: Minimum Tax for the tax year 2013
I28: =+I23-I25 -> 0 | K28: =+K23-K25 -> 0 | M28: 138945
B30: (2 | C30: Minimum tax u/s 113 on sale and other income @ 1.5 % | I30: =(NOTES!#REF!)*1.5% -> #REF! | K30: =(NOTES!#REF!)*1.25% -> #REF! | M30: ='Tax dep'!N25 -> 3280859.9
B32: (3 | C32: Alternate Corporate Tax @ 17% on Accounting profit | I32: =IF(I7>0,I7*0.17,0) -> 0 | K32: 0 | M32: =M30-M28 -> 3141914.9
B34: Total Liability | I34: =MAX(I28,I30,I32) -> #REF! | K34: =MAX(K28,K30,K32) -> #REF! | N34: =M30-M28 -> 3141914.9
A36: Tax already paid
C38: Opening balance | I38: 0 | K38: 0
B40: Add: Tax deducted / collected :
C41: Bank profit & Cash Withdrawls | I41: ='Trial 2020'!B92-NOTES!#REF! -> #REF! | K41: 15041 | N41: 132136 | O41: =+K41-N41 -> -117095
C42: WHT-utilities | I42: ='Trial 2020'!B93 -> 78845
B44: Total deduction | I44: =SUM(I41:I43) -> #REF! | K44: =SUM(K41:K43) -> 15041
B46: Total Refundable | I46: =I44+I38 -> #REF! | K46: =K44+K38 -> 15041
B47: Admitted tax | I47: =-I34 -> #REF! | K47: =-K34 -> #REF!
B49: Tax Refundable/ (Payable) | I49: =I46+I47 -> #REF! | K49: =K46+K47 -> #REF!

Sheet Def tax
A1: SWIFT MOVERS (PVT) LIMITED
A2: BALANCE SHEET AS AT JUNE 30, 2019
D4: Account base | F4: Tax base | H4: Temporary difference
C5: Note | D5: Rupees | F5: Rupees | H5: Rupees
A8: EQUITY AND LIABILITIES
A10: SHARE CAPITAL AND RESERVES
A12: Authorized Capital | D12: =+SOFP!#REF! -> #REF! | F12: =+D12 -> #REF! | H12: =+F12-D12 -> #REF!
A14: Issued, subscribed and paid up capital | D14: =+SOFP!#REF! -> #REF! | F14: =+D14 -> #REF! | H14: =+F14-D14 -> #REF!
A15: Unappropriated profit | D15: =+SOFP!#REF! -> #REF! | F15: =+D15 -> #REF! | H15: 0
D16: =SUM(D14:D15) -> #REF! | F16: =SUM(F14:F15) -> #REF! | H16: =SUM(H14:H15) -> #REF!
A18: NON-CURRENT LIABILITIES
A20: Share deposit money | D20: =+SOFP!#REF! -> #REF! | F20: =+D20 -> #REF! | H20: =D20-F20 -> #REF!
A21: Liability against asset subject to finance lease | D21: 0 | F21: 0 | H21: =+D21-F21 -> 0
A22: Deferred taxation | D22: 0 | F22: =+D22 -> 0 | H22: 0
D23: =SUM(D20:D22) -> #REF! | F23: =SUM(F20:F22) -> #REF! | H23: =SUM(H21:H22) -> 0
A25: CURRENT LIABILITIES
A26: =[98]B.S!B40 -> Trade and other payables | D26: =+SOFP!#REF! -> #REF! | F26: =D26-(NOTES!#REF!/2) -> #REF! | H26: =+F26-D26 -> #REF! | I26: =+NOTES!#REF!/2 -> #REF!
A27: =[98]B.S!B41 -> Due to related party | D27: =+SOFP!#REF! -> #REF! | F27: =D27 -> #REF! | H27: =D27-F27 -> #REF!
A28: =[98]B.S!B42 -> Current portion of liabilities | H28: =+D28-F28 -> 0
A29: =[98]B.S!B43 -> against asset subject to finance lease | D29: 0 | F29: 0 | H29: =+D29-F29 -> 0
A30: Provision for taxation | D30: 0 | F30: =+D30 -> 0 | H30: =+F30-D30 -> 0
D31: =SUM(D26:D30) -> #REF! | F31: =SUM(F26:F30) -> #REF! | H31: =SUM(H26:H30) -> #REF!
A33: TOTAL EQUITY AND LIABILITIES | D33: =+D31+D23+D16 -> #REF! | F33: =+F16+F23+F31 -> #REF! | H33: =+H16+H23+H31 -> #REF!
A35: ASSETS
A37: NON-CURRENT ASSETS | J37: 778635
A39: Property and equipment | D39: =+SOFP!#REF! -> #REF! | F39: ='Tax dep'!P25 -> 11362701 | H39: =+D39-F39 -> #REF!
A40: Long term deposits | D40: =+SOFP!#REF! -> #REF! | F40: =D40 -> #REF! | H40: =+D40-F40 -> #REF! | J40: =F39 -> 11362701
A41: Deferred taxation | D41: =SOFP!#REF! -> #REF! | F41: =+D41 -> #REF! | H41: =+D41-F41 -> #REF!
D42: =SUM(D39:D41) -> #REF! | F42: =SUM(F39:F41) -> #REF! | H42: =SUM(H39:H41) -> #REF! | J42: =J37-J40 -> -10584066
A43: CURRENT ASSETS
A45: Trade debts | D45: =+SOFP!#REF! -> #REF! | F45: =+D45 -> #REF! | H45: =+D45-F45 -> #REF!
A46: Due from related party | D46: =SOFP!#REF! -> #REF! | F46: =D46 -> #REF! | H46: =+D46-F46 -> #REF!
A47: Advances, prepayments | H47: =+D47-F47 -> 0
A48: and other receivables | D48: =+SOFP!#REF! -> #REF! | F48: =D48 -> #REF! | H48: =+D48-F48 -> #REF!
A49: Income tax refundable | F49: =D49 -> 0 | H49: =+D49-F49 -> 0
A50: Cash and bank balances | D50: =+SOFP!#REF! -> #REF! | F50: =+D50 -> #REF! | H50: =+D50-F50 -> #REF!
D51: =SUM(D45:D50) -> #REF! | F51: =SUM(F45:F50) -> #REF! | H51: =SUM(H45:H50) -> #REF!
A53: TOTAL ASSETS | D53: =D42+D51 -> #REF! | F53: =F42+F51 -> #REF! | H53: =H42+H51 -> #REF!
A55: Deferred tax asset | F55: 0.29 | H55: =ROUND(H33*29%,0) -> #REF!
A56: Deferred tax liability | F56: 0.29 | H56: =ROUND(+H53*29%,0) -> #REF!
A58: Net deferred tax asset as on June 30, 2018 | H58: =H56+H55 -> #REF! | I58: =-H58 -> #REF!
A62: Opening Deferred Tax asset | H62: =-SOFP!#REF! -> #REF! | K62: =285640-63980 -> 221660
A64: Difference charged to P & L Expense / (Income) | H64: =+-H62+H58 -> #REF!
J66: =-57435 -> -57435
J68: =J65+J66 -> -57435
J69: =H62 -> #REF!
J70: =J68+J69 -> #REF!

Sheet Tax dep
B1: TAX DEPRECIATION SCHDULE
B3: OPERATING FIXED ASSETS - TANGIBLE
D5: WRITTEN DOWN VALUE | I5: DEPRECIATION | P5: BOOK VALUE | R5: BOOK VALUE | T5: TIMING
I6: INITIAL | K6: WDV AFTER INITIAL DEPRECIATION | L6: NORMAL | P6: As per tax | T6: DIFFERENCES
B7: DESCRIPTION | D7: As at July 1, | F7: Disposals/ | G7: As at June 30, | I7: Rate | J7: Amount | L7: Rate | M7: 43646 | N7: As at June 30, | P7: As at June 30, | R7: As at June 30, | T7: As at June 30,
D8: 2018 | E8: Additions | F8: Transfers | G8: 2019 | I8: % | J8: Rupees | L8: % | M8: Initial | N8: 2019 | P8: 2019 | R8: 2004 | T8: 2004
B12: Furniture and fixtures | D12: 0 | E12: ='FIXED ASSETS'!K11 -> 700000 | F12: 0 | G12: =D12+E12-F12 -> 700000 | J12: 0 | K12: =G12-J12 -> 700000 | L12: 15 | M12: =ROUND((G12-J12)*L12%,0) -> 105000 | N12: =J12+M12 -> 105000 | P12: =G12-N12 -> 595000 | R12: 37651892 | T12: =R12-P12 -> 37056892
K13: =G13-J13 -> 0 | R13: 1.0880771e+08 | T13: =R13-P13 -> 1.0880771e+08
B14: Office equipment | D14: 0 | E14: ='FIXED ASSETS'!K12 -> 112428 | F14: 0 | G14: =D14+E14-F14 -> 112428 | J14: =G14*0.25 -> 28107 | K14: =G14-J14 -> 84321 | L14: 15 | M14: =ROUND((G14-J14)*L14%,0) -> 12648 | N14: =J14+M14 -> 40755 | P14: =G14-N14 -> 71673 | R14: 20555937 | T14: =R14-P14 -> 20484264
K15: =G15-J15 -> 0 | R15: 790392.15 | T15: =R15-P15 -> 790392.15
B16: Computers | D16: 0 | E16: ='FIXED ASSETS'!K13 -> 359358 | F16: 0 | G16: =D16+E16-F16 -> 359358 | J16: =G16*0.25 -> 89839.5 | K16: =G16-J16 -> 269518.5 | L16: 30 | M16: =ROUND((G16-J16)*L16%,0) -> 80856 | N16: =J16+M16 -> 170695.5 | P16: =G16-N16 -> 188662.5 | R16: 177028.12 | T16: =R16-P16 -> -11634.375
F17: 0 | G17: =D17+E17-F17 -> 0
B18: Machinery | D18: 0 | E18: ='FIXED ASSETS'!K14 -> 2890959 | F18: 0 | G18: =D18+E18-F18 -> 2890959 | J18: =G18*0.25 -> 722739.75 | L18: ='FIXED ASSETS'!N14 -> 15 | M18: =ROUND((G18-J18)*L18%,0) -> 325233 | N18: =M18 -> 325233 | P18: =G18-N18 -> 2565726
F19: 0 | G19: =D19+E19-F19 -> 0
B20: Games equipment | D20: 0 | E20: ='FIXED ASSETS'!K15 -> 732000 | F20: 0 | G20: =D20+E20-F20 -> 732000 | J20: =G20*0.25 -> 183000 | L20: ='FIXED ASSETS'!N16 -> 15 | M20: =ROUND((G20-J20)*L20%,0) -> 82350 | N20: =M20 -> 82350 | P20: =G20-N20 -> 649650
B22: Generators | D22: 0 | E22: ='FIXED ASSETS'!K16 -> 1068000 | F22: 0 | G22: =D22+E22-F22 -> 1068000 | J22: =G22*0.25 -> 267000 | L22: =L20 -> 15 | M22: =ROUND((G22-J22)*L22%,0) -> 120150 | N22: =M22 -> 120150 | P22: =G22-N22 -> 947850
M23: =ROUND((G23-J23)*L23%,0) -> 0 | N23: =J23+M23 -> 0 | P23: =G23-N23 -> 0
B24: Leasehold improvement | D24: 0 | E24: ='FIXED ASSETS'!K17 -> 8780816 | F24: 0 | G24: =D24+E24-F24 -> 8780816 | J24: =G24*0.15 -> 1317122.4 | L24: 15 | M24: =ROUND((G24-J24)*L24%,0) -> 1119554 | N24: =M24+J24 -> 2436676.4 | P24: =G24-N24 -> 6344139.6
B25: Rupees: | D25: =SUM(D12:D23) -> 0 | E25: =SUM(E11:E24) -> 14643561 | F25: =SUM(F11:F24) -> 0 | G25: =SUM(G11:G24) -> 14643561 | J25: =SUM(J11:J24) -> 2607808.6 | K25: =G25-J25 -> 12035752 | M25: =SUM(M11:M24) -> 1845791 | N25: =SUM(N11:N24) -> 3280859.9 | O25: =SUM(O11:O24) -> 0 | P25: =SUM(P11:P24) -> 11362701 | R25: 1.8436438e+08 | T25: =SUM(T12:T24) -> 1.6712762e+08
K26: =G26-J26 -> 0
B27: Rupees: 2003 | D27: 8046171 | E27: 8618559 | F27: 0 | G27: 16664730 | K27: =G27-J27 -> 16664730 | M27: 0 | N27: 0 | P27: 16664730 | R27: 16664730 | T27: 0
E30: =917580 -> 917580
E32: =D25-E30 -> -917580

Sheet Trial 2020
A2: Food Caravan (Private) Limited
A3: Trial Balance
A4: As at 30/06/2020
A5: Accrual basis
B6: 30/06/2020
B7: Debit | C7: Credit
A8: Revenue
A9: Bank Profit | C9: 21951.23
A10: Gain/Loss on Disposal
A11: Other Income | C11: 15550
A12: Sales
A13: Sales - Outlet | C13: 7311902 | D13: =C13*0.16 -> 1169904.3
A14: Expenses
A15: Deprecialion Lease Vehicle
A16: Depreciation Computer Equipment
A17: Depreciation Furniture & Fixture
A18: Depreciation Office Equipment
A19: Depreciation Office Vehicle
A20: Fixed assets - depreciation
A21: Intangible assets - amortization
A22: Official Entertainment exp | B22: 5833
A23: Restaurants Employee Meals Expense | B23: 327809
A24: Annual Audit Fee
A25: Consultancy Fee
A26: Fee & Subscription Charges | B26: 1605
A27: Misc. Professional Expense | B27: 496566
A28: Courier & Postage | B28: 570
A29: Decoration Expense
A30: Food Testing | B30: 67284
A31: Fumigation
A32: Insurance Expense | B32: 280636
A33: Misc. Expense | B33: 872634
A34: Restaurant Cleaning Items | B34: 92961
A35: Security Expense | B35: 273333
A36: Uniform Expense
A37: Printing Expense | B37: 48225
A38: Stationary Expense | B38: 208883
A39: Rent - Head Office
A40: Rent - Outlets | B40: 4200000
A41: Equipment Maintenance
A42: Repair & Maintenance - Outlets | B42: 894086
A43: Vehicle Repair & Maintennace | B43: 50000
A44: Bonus
A45: Medical | B45: 25000
A46: Provision for Gratuity - Head Office | B46: 756000
A47: Provision for Gratuity - Restaurant | B47: 30000
A48: Salary - Head Office Staff | B48: 6859831
A49: Salary - Restaurant Staff | B49: 4591494
A50: Deferred Tax Exp
A51: Provision for Tax-Normal
A52: Provision for Tax-PTR
A53: Fuel Allowance & Reimbursement | B53: 288214
A54: Transportation & Carriage | B54: 29103
A55: Traveling & Hotel | B55: 30579
A56: Electricity Bill | B56: 2426489
A57: Generator Diesel | B57: 181851
A58: LPG | B58: 418284
A59: Mobile Phone Bills | B59: 75415
A60: PTCL & Internet | B60: 106598
A61: Sui Gas
A62: Utilities Expenses
A63: Water & Allied Charges | B63: 27988
A64: Cost of Sale | B64: 4188509.7
A65: Inventory - cost
A66: Bank Charges | B66: 77057.14
A67: Bank Charges - Credit/Debit Card | B67: 2490.36
A68: Pool - Employee Salaries
A69: Pool - Utility Expenses
A70: Advertisement & Promotion | B70: 2856440
A71: Commission - Cheetay | B71: 2083.46
A72: Commission - Food Panda | B72: 57973.79
A73: Software maintenance | B73: 32000
A74: Web service & Networking | B74: 31287 | D74: =SUM(B19:B74) -> 30915112 | E74: =D74-B64 -> 26726603 | F74: =E74-NOTES!#REF! -> #REF!
A75: Net profit (loss) | C75: 23565709
A76: Assets
A77: Advance to Supplier
A78: Prepaid Expenses
A79: Cash at Bank | B79: 783471.42
A80: Cash on Hand | B80: 45284
B82: Debit | C82: Credit
A83: Accounts Receivable | B83: 11954.47
A84: Advance to Employees | B84: 120000
A85: Other Receivables
A86: Trade Receivables
A87: Income Tax Refund From Govt
A88: Cash Withdrawal
A89: Motor Vehicle Token Tax
A90: Sales Tax Adjustable | B90: 2829.86
A91: Vehicle purchase
A92: W.Tax on Bank Profit & Cash Withdrawal | B92: 22739.45
A93: WHT on Utilities | B93: 78845
A94: Stores & Spares | B94: 302130
A95: Inventory on hand | B95: 2823450.9
A96: Intangible assets | B96: 136126 | E96: =C97/B96 -> 0.12481084
A97: Intangible assets, accumulated amortization | C97: 16990
A98: Security Deposits | B98: 1200000
A99: Fixed assets | B99: 15957761 | D99: =B99-C100 -> 15096324
A100: Fixed assets, accumulated depreciation | C100: 861437
A101: Liabilities
A102: Accounts payable | B102: 51550.23 | G102: =SUM(B79:B102) -> 21536142 | H102: =G102-C97-C100 -> 20657715
...

Sheet D.tax 20
A1: HM HOLDING (PRIVATE) LIMITED | N1: Deferred tax 2017
A2: DEFERRED TAXATION | M2: Opening | N2: =[99]BS!N25 -> 278962 | O2: Opening | R2: 0
A3: FOR THE PERIOD ENDED JUNE 30, 2020
M4: Oci charge | N4: 0 | O4: Defferred Tax expenses | R4: 2230288
A5: DEFERRED TAX | C5: 2020 | M5: Charge to PL | N5: =+P8-N4 -> 0
F6: Temporary Difference | K6: =Y6 -> Transfer to | S6: 2010 | Y6: Transfer to
C7: Accounting Base | D7: Tax Base | E7: Permanent difference | F7: Taxable Temporary Difference | G7: Deductible Temporary difference | H7: Deferred tax liability/(asset) @ 29% | K7: =Y7 -> Deferred Tax Income | L7: =Z7 -> Equity (remaining balance) | M7: Closing | N7: =H26 -> #REF! | O7: Closing | S7: Accounting Base | T7: Tax Base | U7: Permanent difference | V7: Timing Difference | W7: Deferred tax liability/(asset) @ 35% | Y7: Deferred Tax Income | Z7: Equity (remaining balance)
H8: 0.29 | I8: 0 | N8: =SUM(N2:N7) -> #REF! | R8: =SUM(R2:R7) -> 2230288
A9: Assets
A11: Land
A12: Fixed assets and Investment property ( Other than land) | C12: ='FA-04'!F5 -> 850000 | D12: ='Tax Dep. Sch-20'!L27 -> 10213288 | E12: 0 | F12: =C12-D12 -> -9363288.3 | G12: 0 | H12: =F12*$H$8 -> -2715353.6 | S12: 8.2480867e+08 | T12: 267072633 | U12: 99600000 | V12: 4.5813604e+08 | W12: 160347613 | AB12: 99600000
A13: Building | C13: 0 | D13: 0 | E13: 0 | F13: =C13-D13 -> 0 | H13: =F13*$H$8 -> 0
A14: Biological Assets | C14: 0 | D14: 0 | E14: 0 | F14: =C14-D14 -> 0 | G14: 0 | H14: =F14*$H$8 -> 0 | S14: 4325418 | T14: 0 | V14: -4325418 | W14: -1513896
A15: Long Term Invetments | C15: 0 | D15: =C15 -> 0 | E15: 0 | F15: 0 | G15: 0 | H15: 0
A16: Trade debts | C16: 0 | D16: 0 | E16: 0 | F16: =C16-D16 -> 0 | G16: =C16-D16-E16 -> 0 | H16: =F16*$H$8 -> 0 | S16: 1.5035261e+08 | T16: 1.5663522e+08 | V16: -6282609.8 | W16: -2198913
A17: Advance to employees | C17: 0 | D17: 0 | E17: 0 | F17: =C17-D17 -> 0 | G17: =C17-D17-E17 -> 0 | H17: =F17*$H$8 -> 0 | S17: 3050336.5 | T17: 8317277.5 | V17: -5266941 | W17: -1843429
A18: Advance to Suppliers | C18: 0 | D18: 0 | E18: 0 | H18: =G18*$H$8 -> 0 | S18: 43705439 | T18: 43705439 | V18: 0 | W18: 0
A20: Liabilities | W20: 0
A21: Turnover tax-Finance Act 2004 Note - 1 | G21: 0 | K21: =D21 -> 0 | W21: 0
A22: Deferred gratuity | C22: 0 | D22: 0 | E22: 0 | F22: 0 | G22: =C22-D22-E22 -> 0 | H22: =-G22*$H$8 -> 0 | S22: 5006101 | V22: -5006101 | W22: -1752135
A23: Loss for the year | C23: 0 | D23: =#REF! -> #REF! | E23: 0 | F23: 0 | G23: =C23-D23-E23 -> #REF! | H23: =-G23*$H$8 -> #REF!
A24: Turnover tax-Finance Act 2004 Note - 1 | C24: 0 | D24: 0 | G24: =D24 -> 0 | H24: =G24*$H$8 -> 0 | T24: 16265051 | V24: -16265051 | W24: -16265051
A25: Brought forward losses previous period (2019) | C25: 0 | D25: =D33+D34 -> -13569741 | G25: =C25-D25-E25 -> 13569741 | H25: =K21-G25*$H$8 -> -3935224.9 | K25: =H25+H23+K21 -> #REF!
H26: =SUM(H10:H25) -> #REF!
C28: Year | D28: Losses
C29: 2013
C30: 2014
C31: 2015
C32: 2016 | D32: 0
C33: 2018 | D33: 0
C34: 2019 | D34: -13569741
C35: 2020 | D35: =#REF! -> #REF!
C36: Total | D36: =SUM(D32:D35) -> #REF!
A43: Assessed losses | C43: 7103705 | D43: 10084 | E43: 1412660 | G43: =3834601+1334712 -> 5169313 | H43: =SUM(C43:G43) -> 13695762
A44: Upto 2003 | C44: 0 | D44: =(-60710771-8718579-28767141-10044417)*0 -> 0 | G44: =D44 -> 0 | H44: =G44*H8*I8 -> 0 | K44: =G44*0.33 -> 0 | V44: 262456050 | X44: -262456050 | Y44: -91859618
A46: Brought forward losses | C46: 0 | D46: 0 | G46: =D46 -> 0 | H46: =G46*$H$8*$I$8 -> 0 | V46: 89775680 | X46: -89775680 | Y46: -31421488
A47: Current year profit (unassessed) | D47: ='[99]Tax Provision-17'!C31 -> #REF! | G47: =D47 -> #REF! | H47: =G47*$H$8 -> #REF!
A48: Current year profit (unassessed)
A49: Current year profit (unassessed)
A50: Deferred tax (asset) /liability | H50: =SUM(H12:H47) -> #REF! | Y50: 29018543
A51: Opening liability | M51: =+#REF! -> #REF! | W51: =(35-34)%*V51 -> 0
A52: Effect of impairment | M52: 0
A53: P & L charge | M53: =SUM(M50:M52) -> #REF! | N53: =H50-M53 -> #REF!
C55: 2017 | D55: 2016 | E55: 2015 | G55: Total
A56: exports sales | C56: =+#REF! -> #REF! | D56: =+#REF! -> #REF! | E56: 9540702 | G56: =+(C56+D56+E56) -> #REF! | H56: =+G56/$G$59*100 -> #REF! | K56: Closing liabiliy | M56: =H50 -> #REF! | U56: =H50-M53 -> #REF!
A57: local sales | C57: =+#REF! -> #REF! | D57: =+#REF! -> #REF! | E57: 1.6418826e+09 | G57: =+(C57+D57+E57) -> #REF! | H57: =+G57/$G$59*100 -> #REF! | K57: Opening liability | M57: =-M51 -> #REF!
A58: Waste | C58: =+#REF! -> #REF! | D58: =+#REF! -> #REF! | E58: 31896137 | G58: =+(C58+D58+E58) -> #REF! | H58: =+G58/$G$59*100 -> #REF! | K58: rate change | M58: =M51/33*3*0 -> #REF!
C59: =+C56+C57+C58 -> #REF! | D59: =+D56+D57+D58 -> #REF! | E59: =SUM(E56:E58) -> 1.6833195e+09 | G59: =+G56+G57+G58 -> #REF! | H59: =SUM(H57:H58) -> #REF! | K59: Transfer frm surplus | M59: =-#REF! -> #REF! | U59: =M60-M59-M58 -> #REF! | W59: 0
K60: Profit exp | M60: =SUM(M56:M59) -> #REF! | N60: Total
M61: oci | N61: =-#REF! -> #REF! | W61: -78518364
M62: p& L | N62: =M60-N61 -> #REF! | U62: =+N53-N62 -> #REF! | V62: =+U62+M51 -> #REF! | W62: -78518364 | X62: @ 35% | Y62: -27481427
W63: =+N62-H50 -> #REF!
G64: Tax on taxable income | H64: 2017 | M64: Turnover as per income tax return | U64: 2010 | V64: Turnover as per income tax return
A65: Note : 1 Turnover tax-Finance Act 2004
C66: 2006 | H66: =3177898.635*0 -> 0 | M66: =635579727*0 -> 0 | U66: 3181170 | V66: 636234000 | W66: 654273 | X66: 228995.55
C67: 2009 | M67: 955367397 | N67: =M67*0.005 -> 4776837 | U67: 3127623 | V67: 625524600 | W67: 113670 | X67: 39784.5
C68: 2010 | E68: =H68-G68 -> 0 | G68: 0 | M68: 999307273 | N68: =M68*0.005 -> 4996536.4 | U68: 4776837 | V68: 955367400 | W68: 3 | X68: 1.05
C69: 2011 | M69: 1458437901 | N69: =M69*0.005 -> 7292189.5 | U69: 5179420.6 | V69: 1035884126 | W69: 36576853 | X69: 12801899
C70: 2012 | G70: 0 | H70: =+E70 -> 0 | M70: 2306513029 | N70: =M70*0.01 -> 23065130 | U70: 0
C71: =C70+1 -> 2013 | E71: 11964166 | G71: 0 | H71: =+E71 -> 11964166 | M71: 1675478440 | N71: =M71*0.01 -> 16754784
C72: =C71+1 -> 2014 | E72: 21860323 | G72: 0 | H72: =+E72 -> 21860323 | M72: =+'[99]Tax Provision-17'!E41 -> 1.7432062e+09 | N72: =M72*0.005 -> 8716031.2
C73: =C72+1 -> 2015 | E73: =+N73 -> 16737788 | H73: =+E73 -> 16737788 | M73: =1641882640+31896137 -> 1673778777 | N73: =M73*0.01 -> 16737788
C74: 2016 | E74: =+N74 -> #REF! | H74: =+E74 -> #REF! | M74: =+#REF!+#REF! -> #REF! | N74: =M74*0.01 -> #REF!
C75: 2017 | E75: =N75 -> #REF! | H75: =+E75 -> #REF! | M75: =+#REF! -> #REF! | N75: =M75*0.01 -> #REF!
E76: =SUM(E68:E75) -> #REF! | H76: =SUM(H68:H75) -> #REF! | M76: =SUM(M66:M75) -> #REF! | U76: 16265051
K78: ='[99]Tax Provision-17'!C47 -> #REF!
G79: ='[99]Tax Provision-17'!C31*0.35 -> #REF! | H79: =G79-'[99]Tax Provision-17'!C45 -> #REF!
V81: Deferred tax 2016
W82: Opening | X82: =+M51 -> #REF!
G83: =#REF!*0.35 -> #REF! | W83: On surplus | X83: =+#REF! -> #REF!
G84: =#REF!*0.35 -> #REF! | U84: Oci charge | V84: =+#REF! -> #REF!
U85: Charge to PL | V85: =+X88-V84 -> #REF!
U87: Closing | V87: 0 | W87: Closing | X87: =+-M60 -> #REF!
V88: =SUM(V82:V87) -> #REF! | X88: =SUM(X82:X87) -> #REF!

Sheet Tax Dep. Sch-20
B2: =#REF! -> #REF! | L2: ANNEX - A
B3: Tax Depreciation Schedule
B4: Tax Year 2020
C6: W.D.V | H6: D E P R E C I A T I O N | L6: Book Value
B7: Description | C7: As at July 01, | D7: Addition | E7: Additions | F7: Disposals / | G7: As at June 30, | H7: Rate | I7: Initial Allowance | J7: Charge | K7: As at June 30, | L7: As at June 30,
C8: 2019 | D8: New Machinery | F8: Adjustments | G8: 2020 | H8: % | J8: for the Year | K8: 2020 | L8: 2020
B11: Building | C11: 0 | F11: 0 | G11: =+C11+E11-F11 -> 0 | H11: 10 | I11: =E11*50% -> 0 | J11: =(G11-I11)*H11% -> 0 | K11: =I11+J11 -> 0 | L11: =+G11-K11 -> 0
B13: Office Equipments | C13: 71673 | E13: 16200 | F13: 0 | G13: =+C13+E13-F13 -> 87873 | H13: 15 | I13: 0 | J13: =(G13-I13)*H13% -> 13180.95 | K13: =I13+J13 -> 13180.95 | L13: =+G13-K13 -> 74692.05
B15: Building | C15: 6717325 | E15: 0 | F15: 0 | G15: =+C15+E15-F15 -> 6717325 | H15: 10 | I15: =E15*15% -> 0 | J15: =(G15-I15)*H15% -> 671732.5 | K15: =I15+J15 -> 671732.5 | L15: =(G15-K15) -> 6045592.5
B17: Computer Equipments | C17: 299701 | F17: 0 | G17: =+C17+E17-F17 -> 299701 | H17: 30 | I17: =E17*25% -> 0 | J17: =(G17-I17)*H17% -> 89910.3 | K17: =J17+I17 -> 89910.3 | L17: =(G17-K17) -> 209790.7
B19: Electric Equipment | C19: 0 | F19: 0 | G19: =+C19+E19-F19 -> 0 | H19: 15 | I19: =E19*25% -> 0 | J19: =(G19-I19)*H19% -> 0 | K19: =I19+J19 -> 0 | L19: =(G19-K19) -> 0
B21: Furniture & Fixtures | C21: 595000 | E21: 38000 | F21: 0 | G21: =+C21+E21-F21 -> 633000 | H21: 15 | I21: 0 | J21: =(G21-I21)*H21% -> 94950 | K21: =I21+J21 -> 94950 | L21: =(G21-K21) -> 538050
B23: Plant & Machinery | C23: 2990486 | E23: =70000+1190000 -> 1260000 | F23: 0 | G23: =+C23+E23-F23 -> 4250486 | H23: 15 | I23: =E23*25% -> 315000 | J23: =(G23-I23)*H23% -> 590322.9 | K23: =(I23+J23) -> 905322.9 | L23: =(G23-K23) -> 3345163.1
B25: Vehicles not plying for hire | C25: 0 | E25: 0 | F25: 0 | G25: =+C25+E25-F25 -> 0 | H25: 15 | I25: 0 | J25: =((G25-I25)*H25%) -> 0 | K25: =I25+J25 -> 0 | L25: =(G25-K25) -> 0
B27: 2020 Rupees | C27: =SUM(C10:C26) -> 10674185 | D27: =SUM(D10:D26) -> 0 | E27: =SUM(E10:E26) -> 1314200 | F27: =SUM(F10:F26) -> 0 | G27: =SUM(G10:G26) -> 11988385 | I27: =SUM(I10:I26) -> 315000 | J27: =SUM(J10:J26) -> 1460096.6 | K27: =SUM(K10:K26) -> 1775096.6 | L27: =SUM(L10:L26) -> 10213288

Sheet GI Summary
A2: Food Caravan (Private) Limited
A3: General Ledger Summary
A4: For the period from 01/07/2020 to 30/06/2021
A5: Opening | B5: Total debits | C5: Total credits | D5: Net movement Closing balance
B6: balance
A7: Revenue
A8: Other Income
A9: Bank Profit | C9: - | D9: 11316.47 | E9: 11,316.47 Cr
A10: Event Charges | C10: - | D10: 7465 | E10: 7,465.00 Cr
A11: Other Income | C11: - | D11: 196904 | E11: 196,904.00 Cr
A12: Sales
A13: Sales - Outlet | C13: - | D13: 8080585 | E13: 8,080,585.00 Cr
A14: Expenses
A15: ADMIN & GENERAL EXPENSES
A16: Entertainment
A17: Official Entertainment Expense | C17: 14577 | D17: - | E17: 14,577.00 Dr
A18: Restaurants Employee Meals | C18: 482954 | D18: - | E18: 482,954.00 Dr
A19: Expense
A20: Legal & Professional
A21: Annual Audit Fee | C21: 3750 | D21: - | E21: 3,750.00 Dr
A22: Fee & Subscription Charges | C22: 44333 | D22: - | E22: 44,333.00 Dr
A23: Misc. Professional Expense | C23: 532743 | D23: - | E23: 532,743.00 Dr
A24: Other Expense
A25: Courier & Postage | C25: 7479 | D25: - | E25: 7,479.00 Dr
A26: Decoration Expense | C26: 42095 | D26: - | E26: 42,095.00 Dr
A27: Food Testing | C27: 9161 | D27: - | E27: 9,161.00 Dr
A28: Fumigation | C28: 53100 | D28: - | E28: 53,100.00 Dr
A29: Grocery Expense | C29: 120677 | D29: - | E29: 120,677.00 Dr
A30: Insurance Expense | C30: 263008 | D30: - | E30: 263,008.00 Dr
A31: Misc. Expense | C31: 391313 | D31: - | E31: 391,313.00 Dr
A32: Product Development / | C32: 24378 | D32: - | E32: 24,378.00 Dr
A33: Competitor Check
A34: Restaurant Cleaning Items | C34: 411993 | D34: - | E34: 411,993.00 Dr
A35: Security Expense | C35: 528167 | D35: - | E35: 528,167.00 Dr
A36: Uniform Expense | C36: 294634 | D36: - | E36: 294,634.00 Dr
A37: Printing & Stationary
A38: Printing Expense | C38: 185819 | D38: - | E38: 185,819.00 Dr
A39: Stationary Expense | C39: 140894 | D39: - | E39: 140,894.00 Dr
A40: Rent & Rates
A41: Rent - Outlets | C41: 4030000 | D41: - | E41: 4,030,000.00 Dr
A42: Repair & Maintennace
A43: Equipment Repair & | C43: 146940 | D43: - | E43: 146,940.00 Dr
A44: Maintenance
A45: Repair & Maintenance - Outlets | C45: 1426847 | D45: - | E45: 1,426,847.00 Dr
A46: / HO
A47: Page 1 of 4
A49: Food Caravan (Private) Limited
A50: General Ledger Summary
A51: For the period from 01/07/2020 to 30/06/2021
A52: Opening | B52: Total debits | C52: Total credits | D52: Net movement Closing balance
B53: balance
A54: Vehicle Repair & Maintennace | C54: 40870 | D54: - | E54: 40,870.00 Dr
A55: Salary & Other Benefits
A56: Annual Leave Encashment | C56: 13125 | D56: - | E56: 13,125.00 Dr
A57: EOBI | C57: 62400 | D57: - | E57: 62,400.00 Dr
A58: Medical | C58: 185734 | D58: - | E58: 185,734.00 Dr
A59: Provision for Gratuity - Head | C59: 390325 | D59: - | E59: 390,325.00 Dr
A60: Office
A61: Salary - Head Office Staff | C61: 5697844 | D61: - | E61: 5,697,844.00 Dr
A62: Salary - Restaurant Staff | C62: 6250632 | D62: - | E62: 6,250,632.00 Dr
A63: Taxation
A64: Excess Tax Expense (3% etc.) | C64: 76990 | D64: - | E64: 76,990.00 Dr
A65: Traveling & Conveyance
A66: Fuel - Delivery / Pickups | C66: 246506 | D66: - | E66: 246,506.00 Dr
A67: Fuel Allowance & | C67: 713269 | D67: - | E67: 713,269.00 Dr
A68: Reimbursement
A69: Utilities
A70: Electricity Bill | C70: 3515397 | D70: - | E70: 3,515,397.00 Dr
A71: Generator Diesel | C71: 446305 | D71: - | E71: 446,305.00 Dr
A72: LPG | C72: 596160 | D72: - | E72: 596,160.00 Dr
A73: Mobile Phone Bills | C73: 108123.5 | D73: - | E73: 108,123.50 Dr
A74: PTCL & Internet | C74: 248801.5 | D74: - | E74: 248,801.50 Dr
A75: Sui Gas | C75: 1900 | D75: - | E75: 1,900.00 Dr
A76: Utilities Expenses | C76: 73081 | D76: - | E76: 73,081.00 Dr
A77: Water & Allied Charges | C77: 59854 | D77: - | E77: 59,854.00 Dr
A78: COST OF SALES
A79: Cost of Sale | C79: 5765764.6 | D79: - | E79: 5,765,764.63 Dr
A80: FINANCIAL EXPENSES
A81: Bank Charges | C81: 16253 | D81: - | E81: 16,253.00 Dr
A82: Bank Charges - Credit/Debit Card | C82: 71192.72 | D82: - | E82: 71,192.72 Dr
A83: POOL EXPENSES
A84: Pool - Employee Salaries | C84: 352500 | D84: 352500 | E84: -
A85: Pool - Generator Diesel | C85: 10726 | D85: 10726 | E85: -
A86: Pool - Grocery | C86: 96813 | D86: 96813 | E86: -
A87: Pool - Office Repair & Maintenance | C87: 72340 | D87: 72340 | E87: -
A88: Pool - Security Expense | C88: 57000 | D88: 57000 | E88: -
A89: Pool - Stationary | C89: 27027 | D89: 27027 | E89: -
A90: Pool - Utility Expenses | C90: 213129 | D90: 213129 | E90: -
A91: Pool - Web Services & Networking | C91: 2672 | D91: 2672 | E91: -
A92: SELLING & DISTRIBUTION
A93: Page 2 of 4
A95: Food Caravan (Private) Limited
A96: General Ledger Summary
A97: For the period from 01/07/2020 to 30/06/2021
A98: Opening | B98: Total debits | C98: Total credits | D98: Net movement Closing balance
B99: balance
A100: Commission Expense
A101: Commission - Careem NOW | C101: 42295 | D101: - | E101: 42,295.00 Dr
A102: Commission - Cheetay | C102: 59705.02 | D102: - | E102: 59,705.02 Dr
A103: Commission - Food Panda | C103: 342399.8 | D103: - | E103: 342,399.80 Dr
...

Sheet Entries - 20
A2: Food Caravan (Private) Limited
A3: Entries 2019-2020
A5: Sr. | B5: Description | F5: Dr. | G5: Cr.
A7: 1 | B7: Audit Fee - Accrual
B8: Audit Fee | F8: =NOTES!#REF! -> #REF!
C9: Accrued liabilities | G9: 75000
A10: 2 | B10: Accrued liability paid
B11: Accrued liability | F11: ='Trial 2020'!C103 -> 50000
B12: Tax Expense | F12: 8000
C13: Witholding tax payable | G13: 5800
C14: Askari Bank | G14: 52200
A15: 3 | B15: Depriciation | L15: 665000 | M15: 107949 | N15: 297917 | O15: 2727631 | P15: 704637 | Q15: 1030450 | R15: 8248540
B16: Opening Depriciation
B17: ='FA-04'!D11 -> Land & Building | C17: 665000 | D17: 0.3 | F17: =ROUND(C17*D17,0) -> 199500
B18: ='FA-04'!F11 -> Furniture & Fixtures | C18: 107949 | D18: 0.15 | F18: =ROUND(C18*D18,0) -> 16192
B19: ='FA-04'!H11 -> Plant & Machinery | C19: 297917 | D19: 0.15 | F19: =ROUND(C19*D19,0) -> 44688
B20: ='FA-04'!#REF! -> #REF! | C20: 2727631 | D20: 0.15 | F20: =ROUND(C20*D20,0) -> 409145
B21: ='FA-04'!#REF! -> #REF! | C21: 704637 | D21: 0.15 | F21: =ROUND(C21*D21,0) -> 105696
B22: ='FA-04'!#REF! -> #REF! | C22: 1030450 | D22: 0.15 | F22: =ROUND(C22*D22,0) -> 154568
B23: ='FA-04'!#REF! -> #REF! | C23: 8248540 | D23: 0.15 | F23: =ROUND(C23*D23,0) -> 1237281
C25: Accumulated Depreciation | G25: =SUM(F17:F23) -> 2167070
B26: Addition
B27: =B17 -> Land & Building | F27: 10449.75
B28: =B18 -> Furniture & Fixtures | F28: 2429.75
B29: =B20 -> #REF! | F29: 8750
B30: =B21 -> #REF! | F30: 177375
C31: Accumulated Depreciation | G31: =SUM(F27:F30) -> 199004.5 | I31: =G31+G25 -> 2366074.5 | J31: ='FA-04'!L163 -> 0
A32: 4 | B32: Amortization
B34: Amortization Expense | F34: =-NOTES!#REF! -> #REF!
C35: Accumulated Amortization | G35: =$F$34 -> #REF!
A37: 5 | B37: Stock Consumed
B38: Cost of goods sold (Consumption) | F38: =2823450.87-858659 -> 1964791.9
C39: Stock in trade | G39: 1964791.9
A42: 6 | B42: Bad Debt Expenses | F42: 51550.23
C43: Accounts payable- Write off | G43: 51550.23
A45: 7 | B45: Tax Expense | F45: =#REF! -> #REF!
C46: Provision for taxation | G46: =F45 -> #REF!
A48: 8 | B48: Sales tax payable | F48: 53403
B49: Prepaid expense | F49: 147393
C50: Misc. Expenses | G50: 200796
